ver/processor_defines.sv

// OPCODES
`define OP_REG 7'b011_0011
`define OP_IMM 7'b001_0011
`define OP_LOAD 7'b000_0011
`define OP_STORE  7'b010_0011
`define OP_BRANCH 7'b110_0011
`define OP_JAL 7'b110_1111
`define OP_JALR 7'b110_0111
`define OP_LUI 7'b011_0111
`define OP_AUIPC 7'b001_0111

// ALU Operations
`define ALU_NOP 5'd0
`define ADD 5'd1
`define SUB 5'd2
`define XOR 5'd3
`define OR 5'd4
`define AND 5'd5
`define SLL 5'd6
`define SRL 5'd7
`define SRA 5'd8
`define SLT 5'd9
`define SLTU 5'd10

`define ADDI 5'd16
`define XORI 5'd17
`define ORI 5'd18
`define ANDI 5'd19
`define SLLI 5'd20
`define SRLI 5'd21
`define SRAI 5'd22
`define SLTI 5'd23
`define SLTIU 5'd24

`define LUI 5'd28
`define AUIPC 5'd29

// BRANCH Operations
`define BR_NOP 3'd0
`define BEQ 3'd1
`define BNE 3'd2
`define BLT 3'd3
`define BGE 3'd4
`define BLTU 3'd5
`define BGEU 3'd6

// JUMP Operations
`define JMP_NOP 2'd0
`define JAL 2'd1
`define JALR 2'd2

// LOAD Operations
`define LD_NOP 3'd0
`define LB 3'd1
`define LH 3'd2
`define LW 3'd3
`define LBU 3'd4
`define LHU 3'd5

// STORE Operations
`define STR_NOP 3'd0
`define SB 3'd1
`define SH 3'd2
`define SW 3'd3

// LOAD - STATE MACHINES
`define LOAD_RESET 1'b0
`define READ_MEM 1'b1

// STORE - STATE MACHINES
`define STORE_RESET 1'b0
`define WRITE_MEM 1'b1

// MEM Addr Width
`define MEM_ADDR_WD 10

// FILE Included
`define FILE_INCL 1

ver/decode_jump_inst.sv
`ifndef FILE_INCL
    `include "processor_defines.sv"
`endif

module decode_jump_inst(
    input logic [31:0] instruction_code,

    output logic [4:0] rd,
    output logic [4:0] rs1,
    output logic [20:0] imm,
    output logic [1:0] jump_control
);
logic [6:0] opcode ;
logic [2:0] func3;

always@(*) begin
    rd = instruction_code[11:7];
 
    func3 = instruction_code[14:12];
   
    opcode = instruction_code[6:0];
  
    case(opcode) 
    7'd111 : begin
        imm[20:0] ={instruction_code[31],instruction_code[19:12],instruction_code[20],instruction_code[30:21],1'b0} ;
        jump_control = `JAL; 
        rs1 = 'b0;
    end
    7'd103 :begin
        if(func3 == 'b0) begin
            imm = instruction_code[31:20];
            for(int i = 20 ; i >= 19 ; i = i-1)
            begin
                imm[i] = 1'b0 ;
            end
           rs1 = instruction_code[19:15];

         jump_control = `JALR;
        end
        else begin
            jump_control = `JMP_NOP;
            rs1 = 'b0;
            imm = 'b0;
        end
    end

    default : begin
        jump_control = `JMP_NOP;
        rs1 = 'b0;
        imm = 'b0;
    end
    endcase


end
`ifndef SUBMODULE_DISABLE_WAVES
   initial
     begin
        $dumpfile("./sim_build/decode_jump_inst.vcd");
        $dumpvars(0, decode_jump_inst);
     end
 `endif

endmodule

sim_submodules/sim_build/decode_jump_inst.vcd
$date
	Sun Jul  7 22:50:19 2024
$end
$version
	Icarus Verilog
$end
$timescale
	1ps
$end
$scope module decode_jump_inst $end
$var wire 32 ! instruction_code [31:0] $end
$var reg 3 " func3 [2:0] $end
$var reg 21 # imm [20:0] $end
$var reg 2 $ jump_control [1:0] $end
$var reg 7 % opcode [6:0] $end
$var reg 5 & rd [4:0] $end
$var reg 5 ' rs1 [4:0] $end
$scope begin $ivl_for_loop0 $end
$var integer 32 ( i [31:0] $end
$upscope $end
$upscope $end
$enddefinitions $end
#0
$dumpvars
b0 (
b0 '
b1111 &
b0 %
b0 $
b0 #
b101 "
b10011011000111100101011110000000 !
$end
#1000
b1100111 %
b110 "
b1001 &
b101100001100110110010011100111 !
#2000
b0 %
b0 "
b10101 &
b11100010000110100000101010000000 !
#3000
b101 "
b1100 &
b11111110110011011101011000000000 !
#4000
b11 "
b10001 &
b1111010011111011100010000000 !
#5000
b110 "
b10 &
b11011100001000101110000100000000 !
#6000
b1 $
b110110000101010010010 #
b1101111 %
b0 "
b1001 &
b10101001001110110000010011101111 !
#7000
b1111111001111010010 #
b111 "
b10 &
b111101001001111111000101101111 !
#8000
b0 #
b0 $
b0 %
b110 "
b11100 &
b10101111101010011110111000000000 !
#9000
b101 "
b10011 &
b10001100011001111101100110000000 !
#10000
b110 "
b11101 &
b1100100100000100110111010000000 !
#11000
b1 "
b11100 &
b11100010110110101001111000000000 !
#12000
b1100111 %
b100 "
b101 &
b101101100001111100001011100111 !
#13000
b1 $
b1010110111110101000 #
b1101111 %
b110 "
b10110 &
b1111010100101010110101101101111 !
#14000
b0 #
b0 $
b0 %
b1 "
b1101 &
b1000100001001111001011010000000 !
#15000
b1100111 %
b10 "
b101 &
b111101011100100010001011100111 !
#16000
b0 %
b111 "
b1110 &
b10011000001011111011100000000 !
#17000
b1 $
b1111010101010111110 #
b1101111 %
b10 "
b101 &
b101011111101111010001011101111 !
#18000
b100010000001011001110 #
b0 "
b1101 &
b10101100111000010000011011101111 !
#19000
b0 #
b0 $
b1100111 %
b1 "
b1011 &
b111011010011101001010111100111 !
#20000
b1 $
b101001110101011011100 #
b1101111 %
b110 "
b10 &
b10101101110101001110000101101111 !
#21000
b0 #
b0 $
b0 %
b11 "
b10101 &
b11110110100111101011101010000000 !
#22000
b1100111 %
b100 "
b1001 &
b10101110101010110100010011100111 !
#23000
b111 "
b1101 &
b1101011011100111111011011100111 !
#24000
b0 %
b111 &
b111110011111001111001110000000 !
#25000
b1100111 %
b11110 &
b11000110101101100111111101100111 !
#26000
b1 $
b111000101101100101100 #
b1101111 %
b101 "
b11111 &
b10110010110111000101111111101111 !
#27000
b1000101010111010000 #
b11001 &
b1011101000001000101110011101111 !
#28000
b0 #
b0 $
b0 %
b0 "
b10101 &
b10001111100100011000101010000000 !
#29000
b1100111 %
b111 "
b100 &
b11100111011101100111001001100111 !
#30000
b1 $
b10010111000000000100 #
b1101111 %
b10101 &
b10010010111101011101111 !
#31000
b11010101011100110010 #
b101 "
b11010 &
b1110011001011010101110101101111 !
#32000
b100100101010100001110 #
b10100 &
b11010000111000100101101001101111 !
#33000
b100010010001010010000 #
b10 "
b10 &
b10101001000000010010000101101111 !
#34000
b10 $
b11001 '
b10010 (
b100110010000 #
b1100111 %
b0 "
b11101 &
b10011001000011001000111011100111 !
#35000
b0 #
b0 '
b0 $
b0 %
b10 "
b10011 &
b1010110000111111010100110000000 !
#36000
b0 "
b10101 &
b10010111110100101000101010000000 !
#37000
b1 "
b10000 &
b111010001000111001100000000000 !
#38000
b1 $
b100000000011101101110 #
b1101111 %
b0 "
b10001 &
b11110110111000000000100011101111 !
#39000
b1100110010001100110 #
b110 "
b1011 &
b1000110011001100110010111101111 !
#40000
b11100011110011010000 #
b11 "
b1 &
b1001101000111100011000011101111 !
#41000
b0 #
b0 $
b1100111 %
b100 "
b110 &
b10111110101010100001101100111 !
#42000
b1 "
b11001 &
b1111000101101110001110011100111 !
#43000
b0 %
b110 "
b11 &
b11111000101101110110000110000000 !
#44000
b10 $
b1110 '
b10010 (
b10000010101 #
b1100111 %
b0 "
b10101 &
b1000001010101110000101011100111 !
#45000
b0 #
b0 '
b0 $
b0 %
b100 "
b1111 &
b1001100100011010100011110000000 !
#46000
b1 $
b10110101011001011010 #
b1101111 %
b101 "
b11111 &
b1100101101010110101111111101111 !
#47000
b100101110101010100100 #
b110 "
b10001 &
b10101010010100101110100011101111 !
#48000
b110101000011001010100 #
b0 "
b11011 &
b11100101010010101000110111101111 !
#49000
b101110010101001110100 #
b10 "
b10100 &
b10100111010101110010101001101111 !
#50000
b0 #
b0 $
b0 %
b100 "
b1010 &
b10110101101100100010100000000 !
#51000
b10 "
b11100 &
b11110000111101011010111000000000 !
#52000
b1100111 %
b11 "
b1110 &
b11010110011100101011011101100111 !
#53000
b1 $
b101111011100010100 #
b1101111 %
b111 "
b10011 &
b1110001010000101111100111101111 !
#54000
b0 #
b0 $
b1100111 %
b10 "
b11111 &
b11100011010111000010111111100111 !
#55000
b0 %
b1 "
b10000 &
b10101101100010111001100000000000 !
#56000
b1 $
b100100110010001010 #
b1101111 %
b100 "
b100 &
b1001000101100100100001001101111 !
#57000
b1001111001011101110 #
b111 "
b10001 &
b101110111001001111100011101111 !
#58000
b10 $
b1 '
b10010 (
b11011001100 #
b1100111 %
b0 "
b1101100110000001000100011100111 !
#59000
b0 '
b1 $
b110000110111001111010 #
b1101111 %
b110 "
b11000 &
b11100111101110000110110001101111 !
#60000
b0 #
b0 $
b1100111 %
b1 "
b1111 &
b11111001100111000001011111100111 !
#61000
b100 "
b1000 &
b1111001111000010100010001100111 !
#62000
b0 %
b0 "
b1110 &
b1011100100000010000011100000000 !
#63000
b1 $
b11111110011110000110 #
b1101111 %
b110 "
b10110 &
b1111000011011111110101101101111 !
#64000
b100111001010111101010 #
b1 "
b11001 &
b11011110101000111001110011101111 !
#65000
b0 #
b0 $
b0 %
b10 "
b11 &
b101010000010111010000110000000 !
#66000
b1100111 %
b1 "
b10011 &
b100111011100110001100111100111 !
#67000
b0 %
b111 "
b11011 &
b100100000111100111110110000000 !
#68000
b110 "
b11110 &
b100010111100011110111100000000 !
#69000
b1 $
b1001001010011101100 #
b1101111 %
b1 "
b10110 &
b1001110110001001001101101101111 !
#70000
b0 #
b0 $
b0 %
b110 "
b11110 &
b10110110110000100110111100000000 !
#71000
b1100111 %
b1 "
b111 &
b11000011100101110001001111100111 !
#72000
b1 $
b1101001110101110 #
b1101111 %
b101 "
b11 &
b111010111000001101000111101111 !
#73000
b1110110011100000110 #
b110 "
b11010 &
b1110000011001110110110101101111 !
#74000
b0 #
b0 $
b0 %
b10010 &
b1101001100110001110100100000000 !
#75000
b10 "
b10101 &
b10110001110011110010101010000000 !
#76000
b10 $
b1110 '
b10010 (
b111101100 #
b1100111 %
b0 "
b1011 &
b11110110001110000010111100111 !
#77000
b0 #
b0 '
b0 $
b0 %
b110 "
b10001 &
b1010010010101101110100010000000 !
#78000
b101 "
b10100 &
b11101111111101101000000000 !
#79000
b1100111 %
b1 "
b1000 &
b10100001100111000001010001100111 !
#80000
b10 "
b11110 &
b10000000000001000010111101100111 !
#81000
b1 $
b111011001001100111100 #
b1101111 %
b1 "
b100 &
b10110011110011011001001001101111 !
#82000
b0 #
b0 $
b0 %
b100 "
b11011 &
b100001101101100100110110000000 !
#83000
b1100111 %
b101 "
b1 &
b11111100110011110101000011100111 !
#84000
b1 $
b100110000111100011110 #
b1101111 %
b0 "
b10111 &
b11110001111100110000101111101111 !
#85000
b0 #
b0 $
b0 %
b101 "
b111 &
b1001111001111001101001110000000 !
#86000
b1 $
b1101111001001100 #
b1101111 %
b10011 &
b1100100110100001101100111101111 !
#87000
b0 #
b0 $
b0 %
b110 "
b11011 &
b1100001001101101110110110000000 !
#88000
b1 $
b110001001100011000100 #
b1101111 %
b1 "
b1110 &
b10001100010110001001011101101111 !
#89000
b0 #
b0 $
b1100111 %
b101 "
b1000 &
b11000101111111001101010001100111 !
#90000
b100 "
b11110 &
b1000001111110001100111101100111 !
#91000
b0 %
b11 "
b10110 &
b1001111000000000011101100000000 !
#92000
b101 "
b11101 &
b11100110001111101101111010000000 !
#93000
b1010 &
b10001101001100011101010100000000 !
#94000
b1 $
b11110100100100011010 #
b1101111 %
b100 "
b11110 &
b10001101111110100111101101111 !
#95000
b10101011100110011010 #
b11 "
b11001101110101011111101101111 !
#96000
b0 #
b0 $
b1100111 %
b111 "
b10 &
b1010010011110100111000101100111 !
#97000
b0 %
b10 "
b1000 &
b11101111001011011010010000000000 !
#98000
b1 $
b10011000101011111100 #
b1101111 %
b0 "
b10100 &
b101111110110011000101001101111 !
#99000
b0 #
b0 $
b1100111 %
b111 "
b1 &
b10000110001100111111000011100111 !
