ver/processor_defines.sv

// OPCODES
`define OP_REG 7'b011_0011
`define OP_IMM 7'b001_0011
`define OP_LOAD 7'b000_0011
`define OP_STORE  7'b010_0011
`define OP_BRANCH 7'b110_0011
`define OP_JAL 7'b110_1111
`define OP_JALR 7'b110_0111
`define OP_LUI 7'b011_0111
`define OP_AUIPC 7'b001_0111

// ALU Operations
`define ALU_NOP 5'd0
`define ADD 5'd1
`define SUB 5'd2
`define XOR 5'd3
`define OR 5'd4
`define AND 5'd5
`define SLL 5'd6
`define SRL 5'd7
`define SRA 5'd8
`define SLT 5'd9
`define SLTU 5'd10

`define ADDI 5'd16
`define XORI 5'd17
`define ORI 5'd18
`define ANDI 5'd19
`define SLLI 5'd20
`define SRLI 5'd21
`define SRAI 5'd22
`define SLTI 5'd23
`define SLTIU 5'd24

`define LUI 5'd28
`define AUIPC 5'd29

// BRANCH Operations
`define BR_NOP 3'd0
`define BEQ 3'd1
`define BNE 3'd2
`define BLT 3'd3
`define BGE 3'd4
`define BLTU 3'd5
`define BGEU 3'd6

// JUMP Operations
`define JMP_NOP 2'd0
`define JAL 2'd1
`define JALR 2'd2

// LOAD Operations
`define LD_NOP 3'd0
`define LB 3'd1
`define LH 3'd2
`define LW 3'd3
`define LBU 3'd4
`define LHU 3'd5

// STORE Operations
`define STR_NOP 3'd0
`define SB 3'd1
`define SH 3'd2
`define SW 3'd3

// LOAD - STATE MACHINES
`define LOAD_RESET 1'b0
`define READ_MEM 1'b1

// STORE - STATE MACHINES
`define STORE_RESET 1'b0
`define WRITE_MEM 1'b1

// MEM Addr Width
`define MEM_ADDR_WD 10

// FILE Included
`define FILE_INCL 1

ver/decode_branch_inst.sv
`ifndef FILE_INCL
    `include "processor_defines.sv"
`endif

module decode_branch_inst(
    input logic [31:7] instruction_code,
    output logic [4:0] rs1,
    output logic [4:0] rs2,
    output logic [12:0] imm,
    output logic [2:0] branch_control
);

logic [2:0] func3;
always_comb begin
    rs1  = instruction_code[19:15];
    rs2  = instruction_code[24:20];
    imm  = {instruction_code[31],instruction_code[7], instruction_code[30:25],instruction_code[11:8],1'b0};
    func3 = instruction_code[14:12];


    case(func3)
    3'h0 :  branch_control = `BEQ ;
    3'h1 :  branch_control = `BNE ;
    3'h4 :  branch_control = `BLT ;
    3'h5 :  branch_control = `BGE;
    3'h6 :  branch_control = `BLTU;
    3'h7 :  branch_control = `BGEU ;

    default :  branch_control = `BR_NOP ;
    endcase
end         

`ifndef SUBMODULE_DISABLE_WAVES
   initial
     begin
        $dumpfile("./sim_build/decode_branch_inst.vcd");
        $dumpvars(0, decode_branch_inst);
     end
 `endif
endmodule

sim_submodules/sim_build/decode_branch_inst.vcd
$date
	Fri Jul  5 14:34:17 2024
$end
$version
	Icarus Verilog
$end
$timescale
	1ps
$end
$scope module decode_branch_inst $end
$var wire 25 ! instruction_code [31:7] $end
$var reg 3 " branch_control [2:0] $end
$var reg 3 # func3 [2:0] $end
$var reg 13 $ imm [12:0] $end
$var reg 5 % rs1 [4:0] $end
$var reg 5 & rs2 [4:0] $end
$upscope $end
$enddefinitions $end
#0
$dumpvars
b101 &
b10000 %
b1100111110000 $
b111 #
b110 "
b1001111001011000011110001 !
$end
#1000
b100010000 $
b1100 &
b11111 %
b1000011001111111110000 !
#2000
b101 "
b110 #
b100110010100 $
b11101 &
b1 %
b1100111010000111010101 !
#3000
b10 "
b1 #
b100110001010 $
b11110 &
b1011 %
b1100111100101100101011 !
#4000
b110 "
b111 #
b1101111111110 $
b11111 &
b1 %
b1011111111110000111111111 !
#5000
b100 "
b101 #
b1100110100010 $
b10010 &
b11 %
b1001101100100001110100011 !
#6000
b110 "
b111 #
b1111101100 $
b110 &
b11111 %
b11111001101111111101100 !
#7000
b10 "
b1 #
b110100011100 $
b11001 &
b11 %
b101000110010001100111101 !
#8000
b100 "
b101 #
b1011110100110 $
b11010 &
b1100 %
b1111101110100110010100110 !
#9000
b11 "
b100 #
b1101000000 $
b0 &
b11100 %
b11010000001110010000000 !
#10000
b100 "
b101 #
b1010100011100 $
b10100 &
b10100 %
b1101000101001010010111100 !
#11000
b0 "
b10 #
b11110100100 $
b1100 &
b10010 %
b111101011001001001000100 !
#12000
b1000101000100 $
b1110 &
b11110 %
b1001010011101111001000100 !
#13000
b1 "
b0 #
b1111111000010 $
b1101 &
b10101 %
b1111110011011010100000011 !
#14000
b110 "
b111 #
b111111100110 $
b11110 &
b1111 %
b111111111100111111100111 !
#15000
b0 "
b11 #
b110000000110 $
b10101 &
b1001 %
b100000101010100101100111 !
#16000
b10 #
b1101111011010 $
b111 &
b1000 %
b1011110001110100001011011 !
#17000
b110 "
b111 #
b110000001100 $
b100 &
b1101 %
b100000001000110111101101 !
#18000
b100 "
b101 #
b1111000101000 $
b11 &
b11011 %
b1110001000111101110101001 !
#19000
b1100110110010 $
b110 &
b10011 %
b1001101001101001110110011 !
#20000
b101 "
b110 #
b1100000011010 $
b11111 &
b11 %
b1000000111110001111011011 !
#21000
b1 "
b0 #
b1001100101100 $
b1100 &
b11010 %
b1011001011001101000001100 !
#22000
b0 "
b10 #
b1001111110 $
b1010 &
b10100 %
b10011010101010001011110 !
#23000
b110 "
b111 #
b1100010111010 $
b11 &
b11 %
b1000101000110001111111011 !
#24000
b100 "
b101 #
b101110011110 $
b10011 &
b11101 %
b11100100111110110111111 !
#25000
b10 "
b1 #
b1001010011010 $
b11010 &
b0 %
b1010100110100000000111010 !
#26000
b1 "
b0 #
b1010110001010 $
b10100 &
b1101100101000000000001010 !
#27000
b10 "
b1 #
b111010100000 $
b1101 &
b10011 %
b110101011011001100100001 !
#28000
b101 "
b110 #
b1110101101100 $
b10111 &
b10001 %
b1101011101111000111001101 !
#29000
b1000001010000 $
b0 &
b1010 %
b1000010000000101011010000 !
#30000
b100 "
b101 #
b1000111010 $
b10111 &
b1101 %
b10001101110110110111010 !
#31000
b110 "
b111 #
b100011101110 $
b11001 &
b11111 %
b111110011111111101111 !
#32000
b0 "
b11 #
b1010110 $
b1111 &
b10011111111101110110 !
#33000
b101 "
b110 #
b111010000100 $
b111 &
b10101 %
b110100001111010111000101 !
#34000
b1 "
b0 #
b1011000010100 $
b11010 &
b11110 %
b1110000110101111000010100 !
#35000
b1101010000110 $
b10101 &
b11010 %
b1010100101011101000000111 !
#36000
b110 "
b111 #
b1011010100110 $
b1 &
b11101 %
b1110101000011110111100110 !
#37000
b11 "
b100 #
b10101111100 $
b1010 &
b11001 %
b101011010101100110011100 !
#38000
b10 "
b1 #
b111011111010 $
b10 &
b10100 %
b110111000101010000111011 !
#39000
b1100110110110 $
b11100 &
b1101 %
b1001101111000110100110111 !
#40000
b0 "
b10 #
b1011000000 $
b11010 &
b11111 %
b10110110101111101000000 !
#41000
b10 "
b1 #
b1111100001100 $
b11 &
b1000 %
b1111000000110100000101101 !
#42000
b110 "
b111 #
b1000001110010 $
b1011 &
b1011 %
b1000011010110101111110010 !
#43000
b10 "
b1 #
b100000011010 $
b1101 &
b1010 %
b11010101000111011 !
#44000
b0 "
b10 #
b1110111001000 $
b10001 &
b1101 %
b1101110100010110101001001 !
#45000
b11 "
b100 #
b111110001000 $
b1000 &
b10111 %
b111100010001011110001001 !
#46000
b10 "
b1 #
b1100010000110 $
b100 %
b1000100010000010000100111 !
#47000
b0 "
b10 #
b1011010000110 $
b10101 &
b1011 %
b1110100101010101101000110 !
#48000
b110 "
b111 #
b1111000011110 $
b1101 &
b1101 %
b1110000011010110111111111 !
#49000
b1 "
b0 #
b11100111010 $
b10 %
b111001011010001000011010 !
#50000
b0 "
b10 #
b1000010100000 $
b1 &
b11001 %
b1000101000011100101000000 !
#51000
b11 "
b100 #
b10100100 $
b0 &
b10001 %
b101000001000110000100 !
#52000
b1011010000110 $
b11010 &
b11111 %
b1110100110101111110000110 !
#53000
b1 "
b0 #
b1111010101010 $
b1001 &
b10000 %
b1110101010011000000001011 !
#54000
b0 "
b11 #
b1110010100100 $
b11001 &
b100 %
b1100101110010010001100101 !
#55000
b10 #
b11100010010 $
b1100 &
b10000 %
b111000011001000001010010 !
#56000
b10 "
b1 #
b1111010101100 $
b100 &
b0 %
b1110101001000000000101101 !
#57000
b0 "
b10 #
b110010101010 $
b10 &
b1100 %
b100101000100110001001011 !
#58000
b1 "
b0 #
b1101111011010 $
b1011 &
b10111 %
b1011110010111011100011011 !
#59000
b101 "
b110 #
b10000010010 $
b11100 &
b11010 %
b100000111001101011010010 !
#60000
b100111100110 $
b10001 &
b11 %
b1111100010001111000111 !
#61000
b110 "
b111 #
b1100010110010 $
b1010 &
b1001 %
b1000101010100100111110011 !
#62000
b1111100011100 $
b100 &
b111 %
b1111000001000011111111101 !
#63000
b101 "
b110 #
b110001101110 $
b11110 &
b11101 %
b100011111101110111001111 !
#64000
b110 "
b111 #
b1110000110110 $
b11000 &
b11001 %
b1100001110001100111110111 !
#65000
b10 "
b1 #
b101111111000 $
b11001 &
b1001 %
b11111110010100100111001 !
#66000
b110 "
b111 #
b11011011110 $
b1110 &
b10111 %
b110110011101011111111110 !
#67000
b1001101010000 $
b11111 &
b1000 %
b1011010111110100011110000 !
#68000
b0 "
b11 #
b111100100000 $
b10100 &
b0 %
b111001101000000001100001 !
#69000
b110 "
b111 #
b10100110010 $
b11 &
b11001 %
b101001000111100111110010 !
#70000
b1 "
b0 #
b1101101110010 $
b1110 &
b11 %
b1011011011100001100010011 !
#71000
b0 "
b10 #
b1010101000 $
b10011 &
b11110 %
b10101100111111001001000 !
#72000
b11 #
b1010110110100 $
b11 &
b10011 %
b1101101000111001101110100 !
#73000
b1 "
b0 #
b1010000010010 $
b100 &
b11111 %
b1100000001001111100010010 !
#74000
b101 "
b110 #
b110000000000 $
b1101 &
b11011 %
b100000011011101111000001 !
#75000
b0 "
b11 #
b1011000001100 $
b11110 &
b1101 %
b1110000111100110101101100 !
#76000
b101 "
b110 #
b100101010000 $
b1111 &
b110 %
b1010011110011011010001 !
#77000
b1111011110110 $
b101 &
b11 %
b1110111001010001111010111 !
#78000
b100 "
b101 #
b111000011110 $
b10011 &
b0 %
b110000100110000010111111 !
#79000
b0 "
b11 #
b10011111000 $
b11101 &
b11101 %
b100111111011110101111000 !
#80000
b10 "
b1 #
b1001010011010 $
b1111 &
b110 %
b1010100011110011000111010 !
#81000
b0 "
b10 #
b110000010110 $
b101 &
b1010 %
b100000001010101001010111 !
#82000
b100 "
b101 #
b11011001010 $
b10100 &
b1100 %
b110110101000110010101010 !
#83000
b0 "
b10 #
b10100010110 $
b10111 &
b10100 %
b101000101111010001010110 !
#84000
b110 "
b111 #
b1001101110100 $
b10110 &
b11110 %
b1011011101101111011110100 !
#85000
b1 "
b0 #
b1111010011000 $
b1111 &
b11111 %
b1110100011111111100011001 !
#86000
b101 "
b110 #
b111010010110 $
b11101 &
b10110 %
b110100111011011011010111 !
#87000
b1 "
b0 #
b1001011100110 $
b11 &
b11110 %
b1010111000111111000000110 !
#88000
b0 "
b11 #
b11100001010 $
b1111 &
b1101 %
b111000011110110101101010 !
#89000
b101 "
b110 #
b1111100110100 $
b11110 &
b1100 %
b1111001111100110011010101 !
#90000
b10 "
b1 #
b101011000 $
b1 &
b0 %
b1010000010000000111000 !
#91000
b0 "
b10 #
b1111000111010 $
b10101 &
b10101 %
b1110001101011010101011011 !
#92000
b10 "
b1 #
b10000011000 $
b11111 &
b1011 %
b100000111110101100111000 !
#93000
b11 "
b100 #
b1100100000010 $
b10100 &
b11 %
b1001000101000001110000011 !
#94000
b0 "
b11 #
b110010110 $
b10110 &
b11001 %
b1100101101100101110110 !
#95000
b1100101011010 $
b11011 &
b101 %
b1001010110110010101111011 !
#96000
b101 "
b110 #
b1111101001110 $
b1 &
b11111 %
b1111010000011111111001111 !
#97000
b0 "
b11 #
b1011100000000 $
b1101 &
b0 %
b1111000011010000001100000 !
#98000
b110 "
b111 #
b111110100 $
b11110 &
b10111 %
b1111111101011111110100 !
#99000
b1 "
b0 #
b1010111001100 $
b10001 &
b10 %
b1101110100010001000001100 !
