ver/processor_defines.sv

// OPCODES
`define OP_REG 7'b011_0011
`define OP_IMM 7'b001_0011
`define OP_LOAD 7'b000_0011
`define OP_STORE  7'b010_0011
`define OP_BRANCH 7'b110_0011
`define OP_JAL 7'b110_1111
`define OP_JALR 7'b110_0111
`define OP_LUI 7'b011_0111
`define OP_AUIPC 7'b001_0111

// ALU Operations
`define ALU_NOP 5'd0
`define ADD 5'd1
`define SUB 5'd2
`define XOR 5'd3
`define OR 5'd4
`define AND 5'd5
`define SLL 5'd6
`define SRL 5'd7
`define SRA 5'd8
`define SLT 5'd9
`define SLTU 5'd10

`define ADDI 5'd16
`define XORI 5'd17
`define ORI 5'd18
`define ANDI 5'd19
`define SLLI 5'd20
`define SRLI 5'd21
`define SRAI 5'd22
`define SLTI 5'd23
`define SLTIU 5'd24

`define LUI 5'd28
`define AUIPC 5'd29

// BRANCH Operations
`define BR_NOP 3'd0
`define BEQ 3'd1
`define BNE 3'd2
`define BLT 3'd3
`define BGE 3'd4
`define BLTU 3'd5
`define BGEU 3'd6

// JUMP Operations
`define JMP_NOP 2'd0
`define JAL 2'd1
`define JALR 2'd2

// LOAD Operations
`define LD_NOP 3'd0
`define LB 3'd1
`define LH 3'd2
`define LW 3'd3
`define LBU 3'd4
`define LHU 3'd5

// STORE Operations
`define STR_NOP 3'd0
`define SB 3'd1
`define SH 3'd2
`define SW 3'd3

// LOAD - STATE MACHINES
`define LOAD_RESET 1'b0
`define READ_MEM 1'b1

// STORE - STATE MACHINES
`define STORE_RESET 1'b0
`define WRITE_MEM 1'b1

// MEM Addr Width
`define MEM_ADDR_WD 10

// FILE Included
`define FILE_INCL 1

ver/decode_store_inst.sv
`ifndef FILE_INCL
    `include "processor_defines.sv"
`endif

module decode_store_inst(
    input logic [31:7] instruction_code,
    output logic [4:0] rs1,
    output logic [4:0] rs2,
    output logic [11:0] imm,
    output logic [2:0] store_control
);
logic [2:0] func3;
always_comb begin
    rs1  = instruction_code[19:15];
    rs2  = instruction_code[24:20];
    imm  = {instruction_code[31:25], instruction_code[11:7]};
    func3 = instruction_code[14:12];


    case(func3)
    3'h0 :  store_control = `SB ;
    3'h1 :  store_control = `SH ;
    3'h2 :  store_control = `SW ;
    default :  store_control = `STR_NOP ;
    endcase
end
`ifndef SUBMODULE_DISABLE_WAVES
   initial
     begin
        $dumpfile("./sim_build/decode_store_inst.vcd");
        $dumpvars(0, decode_store_inst);
     end
 `endif

endmodule

sim_submodules/sim_build/decode_store_inst.vcd
$date
	Fri Jul  5 14:15:05 2024
$end
$version
	Icarus Verilog
$end
$timescale
	1ps
$end
$scope module decode_store_inst $end
$var wire 25 ! instruction_code [31:7] $end
$var reg 3 " func3 [2:0] $end
$var reg 12 # imm [11:0] $end
$var reg 5 $ rs1 [4:0] $end
$var reg 5 % rs2 [4:0] $end
$var reg 3 & store_control [2:0] $end
$upscope $end
$enddefinitions $end
#0
$dumpvars
b0 &
b10110 %
b11100 $
b101110110011 #
b11 "
b1011101101101110001110011 !
$end
#1000
b110 "
b110001110101 #
b1010 %
b1011 $
b1100011010100101111010101 !
#2000
b111 "
b101100010100 #
b1110 %
b10010 $
b1011000011101001011110100 !
#3000
b101 "
b110111100111 #
b11000 %
b10000 $
b1101111110001000010100111 !
#4000
b100 "
b100010010 #
b10101 %
b11100 $
b1000101011110010010010 !
#5000
b11 &
b10 "
b110011000111 #
b1001 %
b10000 $
b1100110010011000001000111 !
#6000
b1 &
b0 "
b111010011000 #
b1 %
b0 $
b1110100000010000000011000 !
#7000
b10000010011 #
b1111 %
b11111 $
b100000011111111100010011 !
#8000
b111111000000 #
b1001 %
b11011 $
b1111110010011101100000000 !
#9000
b0 &
b111 "
b1010110 #
b100 %
b10000 $
b10001001000011110110 !
#10000
b11 "
b101010001001 #
b10100 %
b1100 $
b1010100101000110001101001 !
#11000
b11101001010 #
b11001 %
b111010110010110001101010 !
#12000
b1 &
b0 "
b10100100000 #
b1110 %
b11 $
b101001011100001100000000 !
#13000
b0 &
b101 "
b100100010111 #
b10001 %
b10100 $
b1001000100011010010110111 !
#14000
b1 &
b0 "
b101110100100 #
b1111 %
b1 $
b1011101011110000100000100 !
#15000
b0 &
b11 "
b110101100011 #
b100 %
b10111 $
b1101011001001011101100011 !
#16000
b11 &
b10 "
b101000100101 #
b10101 %
b11 $
b1010001101010001101000101 !
#17000
b0 &
b111 "
b110011111001 #
b1010 %
b1010 $
b1100111010100101011111001 !
#18000
b1 &
b0 "
b101011110110 #
b0 %
b11000 $
b1010111000001100000010110 !
#19000
b10 &
b1 "
b11101100111 #
b101 %
b101 $
b111011001010010100100111 !
#20000
b11001101011 #
b11100 %
b100 $
b110011111000010000101011 !
#21000
b0 &
b111 "
b111011000110 #
b11 %
b11 $
b1110110000110001111100110 !
#22000
b1 &
b0 "
b101101010000 #
b101 %
b11001 $
b1011010001011100100010000 !
#23000
b0 &
b100 "
b111100011111 #
b10100 %
b1101 $
b1111000101000110110011111 !
#24000
b111 "
b110100110100 #
b101 %
b11101 $
b1101001001011110111110100 !
#25000
b11110101101 #
b100 %
b11 $
b111101001000001111101101 !
#26000
b10 &
b1 "
b1111000110 #
b1101 %
b1010 $
b11110011010101000100110 !
#27000
b1 &
b0 "
b101010011100 #
b10111 %
b1110 $
b1010100101110111000011100 !
#28000
b0 &
b11 "
b11100110110 #
b10110 %
b10000 $
b111001101101000001110110 !
#29000
b10 &
b1 "
b11000000 #
b10011 %
b11 $
b110100110001100100000 !
#30000
b11 &
b10 "
b100111010010 #
b10110 %
b11010 $
b1001110101101101001010010 !
#31000
b1 &
b0 "
b100001110100 #
b11 %
b110 $
b1000011000110011000010100 !
#32000
b10111110100 #
b11001 %
b1101 $
b101111110010110100010100 !
#33000
b11 &
b10 "
b1001011110 #
b10001 %
b11 $
b10010100010001101011110 !
#34000
b0 &
b111 "
b100001110 #
b1000 %
b11110 $
b1000010001111011101110 !
#35000
b11 &
b10 "
b111111010100 #
b10110 %
b1011 $
b1111110101100101101010100 !
#36000
b0 &
b111 "
b111110101101 #
b111 %
b10010 $
b1111101001111001011101101 !
#37000
b100 "
b11011000110 #
b1 %
b1100 $
b110110000010110010000110 !
#38000
b11 "
b1101 #
b1000 %
b11000 $
b10001100001101101 !
#39000
b111 "
b100101110110 #
b1110 %
b100 $
b1001011011100010011110110 !
#40000
b110011101011 #
b11010 %
b11101 $
b1100111110101110111101011 !
#41000
b110 "
b111010 #
b11111 %
b10011 $
b1111111001111011010 !
#42000
b111 "
b10111101000 #
b10000 %
b10 $
b101111100000001011101000 !
#43000
b100 "
b11100000000 #
b1 %
b1101 $
b111000000010110110000000 !
#44000
b1 &
b0 "
b100001101010 #
b1000 %
b11100 $
b1000011010001110000001010 !
#45000
b0 &
b100 "
b1110011 #
b10 %
b11000101110010010011 !
#46000
b1 &
b0 "
b11010100110 #
b110101000101110000000110 !
#47000
b0 &
b11 "
b100110110001 #
b1 %
b0 $
b1001101000010000001110001 !
#48000
b110 "
b11100001011 #
b11111 %
b11100 $
b111000111111110011001011 !
#49000
b1 &
b0 "
b110010000000 #
b1010 %
b10010 $
b1100100010101001000000000 !
#50000
b0 &
b101 "
b101010000001 #
b11110 $
b1010100010101111010100001 !
#51000
b10 &
b1 "
b111100011100 #
b1110 %
b1011 $
b1111000011100101100111100 !
#52000
b1 &
b0 "
b10101101000 #
b101 %
b11011 $
b101011001011101100001000 !
#53000
b11 &
b10 "
b1011001 #
b1110 %
b10100 $
b10011101010001011001 !
#54000
b0 &
b110 "
b101011111001 #
b1100 %
b11110 $
b1010111011001111011011001 !
#55000
b11 &
b10 "
b1111000 #
b110 %
b1 $
b11001100000101011000 !
#56000
b1 &
b0 "
b111111001010 #
b100 %
b1001 $
b1111110001000100100001010 !
#57000
b11 &
b10 "
b100011000101 #
b11010 %
b1010 $
b1000110110100101001000101 !
#58000
b10 &
b1 "
b100100111001 #
b111 %
b10010 $
b1001001001111001000111001 !
#59000
b0 &
b110 "
b111011010100 #
b10000 %
b10101 $
b1110110100001010111010100 !
#60000
b101 "
b111111001001 #
b1011 %
b1000 $
b1111110010110100010101001 !
#61000
b111 "
b110000110011 #
b1001 %
b11011 $
b1100001010011101111110011 !
#62000
b11 &
b10 "
b11111001000 #
b10011 %
b101 $
b111110100110010101001000 !
#63000
b0 &
b110 "
b1001011010 #
b11001 $
b10010100111100111011010 !
#64000
b11 &
b10 "
b110001101 #
b10000 %
b1011 $
b1100100000101101001101 !
#65000
b0 &
b110 "
b101111001100 #
b11001 %
b0 $
b1011110110010000011001100 !
#66000
b11 &
b10 "
b101110111111 #
b11010 %
b10 $
b1011101110100001001011111 !
#67000
b0 &
b11 "
b11001 #
b101 %
b11111 $
b1011111101111001 !
#68000
b111 "
b1001111010 #
b11100 %
b1001 $
b10011111000100111111010 !
#69000
b1 &
b0 "
b1110010111 #
b11001 %
b10111 $
b11100110011011100010111 !
#70000
b0 &
b111 "
b110000111011 #
b1001 %
b1100001010011011111111011 !
#71000
b100 "
b10111101110 #
b11101 $
b101111010011110110001110 !
#72000
b11 "
b111100011 #
b10011 %
b10 $
b1111100110001001100011 !
#73000
b111001000 #
b1100 %
b10100 $
b1110011001010001101000 !
#74000
b1 &
b0 "
b11000111101 #
b100 %
b11001 $
b110001001001100100011101 !
#75000
b11 &
b10 "
b111111100110 #
b10011 %
b111 $
b1111111100110011101000110 !
#76000
b0 &
b101 "
b111011010010 #
b10010 %
b11110 $
b1110110100101111010110010 !
#77000
b110110011101 #
b11000 %
b100 $
b1101100110000010010111101 !
#78000
b10 &
b1 "
b110111101 #
b10001 %
b11101 $
b1101100011110100111101 !
#79000
b0 &
b110 "
b1001 #
b11000 %
b11000 $
b110001100011001001 !
#80000
b111 "
b1011000000 #
b1000 %
b11010 $
b10110010001101011100000 !
#81000
b1 &
b0 "
b110011111010 #
b11101 %
b11111 $
b1100111111011111100011010 !
#82000
b0 &
b101 "
b101000010011 #
b101 %
b101 $
b1010000001010010110110011 !
#83000
b10 &
b1 "
b111100101101 #
b10000 %
b10110 $
b1111001100001011000101101 !
#84000
b11 &
b10 "
b111001001111 #
b10101 %
b11000 $
b1110010101011100001001111 !
#85000
b1 &
b0 "
b111000110110 #
b1001 %
b10100 $
b1110001010011010000010110 !
#86000
b0 &
b11 "
b100010110 #
b1110 %
b10 $
b1000011100001001110110 !
#87000
b1110101001 #
b11010 %
b101 $
b11101110100010101101001 !
#88000
b11 &
b10 "
b10010111 #
b0 %
b10010 $
b100000001001001010111 !
#89000
b100000101 #
b1110 $
b1000000000111001000101 !
#90000
b10 &
b1 "
b10011111011 #
b11000 %
b10110 $
b100111110001011000111011 !
#91000
b0 &
b111 "
b101111101 #
b10000 %
b10011 $
b1011100001001111111101 !
#92000
b100 "
b10001101001 #
b11111 %
b11110 $
b100011111111111010001001 !
#93000
b111100000101 #
b10110 %
b11001 $
b1111000101101100110000101 !
#94000
b10 &
b1 "
b11 #
b11010 %
b0 $
b110100000000100011 !
#95000
b11 &
b10 "
b111111010001 #
b11110 %
b11101 $
b1111110111101110101010001 !
#96000
b0 &
b101 "
b11000100100 #
b0 %
b10101 $
b110001000001010110100100 !
#97000
b10 &
b1 "
b111001100111 #
b11011 %
b1111 $
b1110011110110111100100111 !
#98000
b0 &
b111 "
b100101101111 #
b10001 %
b10110 $
b1001011100011011011101111 !
#99000
b100 "
b10010000011 #
b1010 %
b11011 $
b100100010101101110000011 !
