ver/processor_defines.sv

// OPCODES
`define OP_REG 7'b011_0011
`define OP_IMM 7'b001_0011
`define OP_LOAD 7'b000_0011
`define OP_STORE  7'b010_0011
`define OP_BRANCH 7'b110_0011
`define OP_JAL 7'b110_1111
`define OP_JALR 7'b110_0111
`define OP_LUI 7'b011_0111
`define OP_AUIPC 7'b001_0111

// ALU Operations
`define ALU_NOP 5'd0
`define ADD 5'd1
`define SUB 5'd2
`define XOR 5'd3
`define OR 5'd4
`define AND 5'd5
`define SLL 5'd6
`define SRL 5'd7
`define SRA 5'd8
`define SLT 5'd9
`define SLTU 5'd10

`define ADDI 5'd16
`define XORI 5'd17
`define ORI 5'd18
`define ANDI 5'd19
`define SLLI 5'd20
`define SRLI 5'd21
`define SRAI 5'd22
`define SLTI 5'd23
`define SLTIU 5'd24

`define LUI 5'd28
`define AUIPC 5'd29

// BRANCH Operations
`define BR_NOP 3'd0
`define BEQ 3'd1
`define BNE 3'd2
`define BLT 3'd3
`define BGE 3'd4
`define BLTU 3'd5
`define BGEU 3'd6

// JUMP Operations
`define JMP_NOP 2'd0
`define JAL 2'd1
`define JALR 2'd2

// LOAD Operations
`define LD_NOP 3'd0
`define LB 3'd1
`define LH 3'd2
`define LW 3'd3
`define LBU 3'd4
`define LHU 3'd5

// STORE Operations
`define STR_NOP 3'd0
`define SB 3'd1
`define SH 3'd2
`define SW 3'd3

// LOAD - STATE MACHINES
`define LOAD_RESET 1'b0
`define READ_MEM 1'b1

// STORE - STATE MACHINES
`define STORE_RESET 1'b0
`define WRITE_MEM 1'b1

// MEM Addr Width
`define MEM_ADDR_WD 10

// FILE Included
`define FILE_INCL 1

ver/decode_imm_inst.sv
`ifndef FILE_INCL
    `include "processor_defines.sv"
`endif

module decode_imm_inst(
    input logic [31:7] instruction_code,

    output logic [4:0] rs1,
    output logic [4:0] rd,
    output logic [11:0] imm,
    output logic [4:0] alu_control
);
logic [2:0] func3;
//logic [6:0] opcode;


always@(*) begin
    rd = instruction_code[11:7];
    rs1 = instruction_code[19:15];
    func3 = instruction_code[14:12];
    imm = instruction_code[31:20];

    
        // case(func3) 
        // 3'b000  : 
        // 3'b001 : begin
        // if(imm[11:5] == 'b0) 
        //  alu_control = `SLLI;
        // end

        // 3'b010 :alu_control = `SLTI;
        //3'b011 :alu_control = `SLTIU;
        //3'b100 :alu_control = `XORI;
       // 3'b101 : begin  if(imm[11:5] == 'b0)
       //             alu_control = `SRLI;
//
       //         else if(imm[11:5] == 7'b0100000)
       //          alu_control = `SRAI;
       // end

        // 3'b110 :alu_control = `ORI;
        // 3'b111 :alu_control = `ANDI;

        // default:alu_control = `ALU_NOP;
               // endcase


        if(func3 == 'b0) begin
            alu_control = `ADDI;
        end
        else if(func3 == 3'b001) begin
            if(imm[11:5] == 'b0) begin
                alu_control = `SLLI;
            end
            else
            alu_control = `ALU_NOP; 
        end
        else if(func3 == 3'b010) begin
            alu_control = `SLTI;
        end
        else if(func3 ==  3'b011) begin
            alu_control = `SLTIU;
        end
        else if(func3 == 3'b100) begin
            alu_control = `XORI;
        end
        else if(func3 == 3'b101) begin
            if(imm[11:5] == 'b0) begin
                alu_control = `SRLI;
            end
            else if(imm[11:5] == 7'b0100000) begin
                alu_control = `SRAI; 
            end
            else begin
                alu_control = `ALU_NOP ;
            end   
        end
        else if(func3 == 3'b110) begin
            alu_control = `ORI;
        end 
        else if(func3 == 3'b111) begin
            alu_control = `ANDI ;
        end
        else begin
            alu_control = `ALU_NOP;
        end

 


    


end

`ifndef SUBMODULE_DISABLE_WAVES
   initial
     begin
        $dumpfile("./sim_build/decode_imm_inst.vcd");
        $dumpvars(0, decode_imm_inst);
     end
 `endif

endmodule

sim_submodules/sim_build/decode_imm_inst.vcd
$date
	Fri Jul  5 14:13:52 2024
$end
$version
	Icarus Verilog
$end
$timescale
	1ps
$end
$scope module decode_imm_inst $end
$var wire 25 ! instruction_code [31:7] $end
$var reg 5 " alu_control [4:0] $end
$var reg 3 # func3 [2:0] $end
$var reg 12 $ imm [11:0] $end
$var reg 5 % rd [4:0] $end
$var reg 5 & rs1 [4:0] $end
$upscope $end
$enddefinitions $end
#0
$dumpvars
b11011 &
b11011 %
b111111001110 $
b0 #
b10000 "
b1111110011101101100011011 !
$end
#1000
b10011 "
b10111010111 $
b111 #
b1011 %
b101110101111101111101011 !
#2000
b10010 "
b10001011111 $
b110 #
b10100 &
b10110 %
b100010111111010011010110 !
#3000
b110001111 $
b11001 &
b10010 %
b1100011111100111010010 !
#4000
b11000 "
b1000111011 $
b11 #
b10111 &
b1100 %
b10001110111011101101100 !
#5000
b10001 "
b10100010111 $
b100 #
b1110 &
b101 %
b101000101110111010000101 !
#6000
b10101 "
b10101 $
b101 #
b1 &
b1101 %
b101010000110101101 !
#7000
b10111 "
b11010111 $
b10 #
b10010 &
b11110 %
b110101111001001011110 !
#8000
b10000 "
b11011101 $
b0 #
b110 &
b1111 %
b110111010011000001111 !
#9000
b10011 "
b111100000011 $
b111 #
b101 &
b10100 %
b1111000000110010111110100 !
#10000
b10001 "
b11000011100 $
b100 #
b1 &
b11001 %
b110000111000000110011001 !
#11000
b101101100011 $
b111 &
b1111 %
b1011011000110011110001111 !
#12000
b10011 "
b111110111111 $
b111 #
b1111 &
b11 %
b1111101111110111111100011 !
#13000
b10100 "
b1000 $
b1 #
b11011 &
b101 %
b10001101100100101 !
#14000
b10101 "
b10 $
b101 #
b10000 &
b10000 %
b101000010110000 !
#15000
b10010 "
b110011010 $
b110 #
b1110 &
b1101 %
b1100110100111011001101 !
#16000
b10101 "
b1011 $
b101 #
b1011 &
b11011 %
b10110101110111011 !
#17000
b10111 "
b111101001111 $
b10 #
b1 &
b10001 %
b1111010011110000101010001 !
#18000
b10010 "
b111010001011 $
b110 #
b1110 &
b10 %
b1110100010110111011000010 !
#19000
b10000 "
b110001001 $
b0 #
b11100 &
b10010 %
b1100010011110000010010 !
#20000
b10011 "
b100001110010 $
b111 #
b111 &
b10101 %
b1000011100100011111110101 !
#21000
b10101 "
b10110 $
b101 #
b100 &
b11 %
b101100010010100011 !
#22000
b10001 "
b110001111000 $
b100 #
b11000 &
b10001 %
b1100011110001100010010001 !
#23000
b11000 "
b111001010000 $
b11 #
b11 &
b10000 %
b1110010100000001101110000 !
#24000
b10111 "
b111001110 $
b10 #
b10111 &
b1101 %
b1110011101011101001101 !
#25000
b10001 "
b10101110111 $
b100 #
b1110 &
b10010 %
b101011101110111010010010 !
#26000
b11000 "
b111111110011 $
b11 #
b10110 &
b11000 %
b1111111100111011001111000 !
#27000
b10001 "
b111001111 $
b100 #
b11001 &
b10001 %
b1110011111100110010001 !
#28000
b10101 "
b111 $
b101 #
b11110 &
b10101 %
b1111111010110101 !
#29000
b10010 "
b100000011111 $
b110 #
b10010 &
b10010 %
b1000000111111001011010010 !
#30000
b10001 "
b111001100101 $
b100 #
b11000 &
b11101 %
b1110011001011100010011101 !
#31000
b10100 "
b10010 $
b1 #
b11011 &
b1000 %
b100101101100101000 !
#32000
b10111 "
b100001011110 $
b10 #
b1110 &
b1011 %
b1000010111100111001001011 !
#33000
b10010 "
b1011001011 $
b110 #
b11101 &
b110 %
b10110010111110111000110 !
#34000
b11000 "
b100101000000 $
b11 #
b1001 &
b10 %
b1001010000000100101100010 !
#35000
b10000 "
b100100101 $
b0 #
b1111 &
b1010 %
b1001001010111100001010 !
#36000
b11000 "
b1011010001 $
b11 #
b11000 &
b10101 %
b10110100011100001110101 !
#37000
b10000 "
b11000010010 $
b0 #
b111 &
b101 %
b110000100100011100000101 !
#38000
b10100 "
b11000 $
b1 #
b1110 &
b11111 %
b110000111000111111 !
#39000
b10001 "
b1010001000 $
b100 #
b10110 &
b11 %
b10100010001011010000011 !
#40000
b10011 "
b100101111010 $
b111 #
b10011 &
b10010 %
b1001011110101001111110010 !
#41000
b0 "
b110001 $
b101 #
b1101 &
b1000 %
b1100010110110101000 !
#42000
b10010 "
b111111100111 $
b110 #
b1010 &
b11000 %
b1111111001110101011011000 !
#43000
b100011001011 $
b110 &
b10111 %
b1000110010110011011010111 !
#44000
b10000 "
b100110110111 $
b0 #
b11101 &
b110 %
b1001101101111110100000110 !
#45000
b11000 "
b110110011000 $
b11 #
b111 &
b11111 %
b1101100110000011101111111 !
#46000
b10011 "
b11100000001 $
b111 #
b101 &
b1 %
b111000000010010111100001 !
#47000
b10100 "
b1000 $
b1 #
b10000 &
b10010 %
b10001000000110010 !
#48000
b11000 "
b101001100101 $
b11 #
b11100 &
b1010011001011110001110010 !
#49000
b0 "
b111111 $
b101 #
b1110 &
b10001 %
b1111110111010110001 !
#50000
b100111 $
b1 &
b1000 %
b1001110000110101000 !
#51000
b11000 "
b110001100001 $
b11 #
b101 &
b100 %
b1100011000010010101100100 !
#52000
b10010 "
b1100100011 $
b110 #
b1010 &
b1111 %
b11001000110101011001111 !
#53000
b10001 "
b110110001010 $
b100 #
b1011 &
b11110 %
b1101100010100101110011110 !
#54000
b101011100101 $
b11110 &
b1100 %
b1010111001011111010001100 !
#55000
b10010 "
b10111 $
b110 #
b1011 &
b101 %
b101110101111000101 !
#56000
b11000111 $
b11000 &
b10011 %
b110001111100011010011 !
#57000
b10000 "
b100011000111 $
b0 #
b1111 &
b1011 %
b1000110001110111100001011 !
#58000
b111011011010 $
b10000 &
b11011 %
b1110110110101000000011011 !
#59000
b10001 "
b111100 $
b100 #
b1000 &
b10010 %
b1111000100010010010 !
#60000
b10010 "
b111111111100 $
b110 #
b10 &
b10101 %
b1111111111000001011010101 !
#61000
b11000 "
b101010110011 $
b11 #
b1000 &
b101 %
b1010101100110100001100101 !
#62000
b10010 "
b1000110 $
b110 #
b1 &
b11110 %
b10001100000111011110 !
#63000
b10001 "
b101100010100 $
b100 #
b10111 %
b1011000101000000110010111 !
#64000
b101110000 $
b111 &
b100 %
b1011100000011110000100 !
#65000
b10100 "
b11110 $
b1 #
b1011 &
b10 %
b111100101100100010 !
#66000
b10001 "
b100111011100 $
b100 #
b10100 &
b11 %
b1001110111001010010000011 !
#67000
b10010 "
b110101111110 $
b110 #
b101 &
b1100 %
b1101011111100010111001100 !
#68000
b10011 "
b10001110101 $
b111 #
b11001 &
b10100 %
b100011101011100111110100 !
#69000
b11000 "
b1111100110 $
b11 #
b11100 &
b10 %
b11111001101110001100010 !
#70000
b10100 "
b10010 $
b1 #
b10010 &
b11001 %
b100101001000111001 !
#71000
b10111 "
b101101001011 $
b10 #
b11111 &
b11100 %
b1011010010111111101011100 !
#72000
b10010 "
b100100011111 $
b110 #
b10111 &
b10011 %
b1001000111111011111010011 !
#73000
b10100 "
b11010 $
b1 #
b1011 &
b10101 %
b110100101100110101 !
#74000
b11000 "
b111011010011 $
b11 #
b1100 &
b111 %
b1110110100110110001100111 !
#75000
b10010 "
b100001010011 $
b110 #
b11101 &
b11 %
b1000010100111110111000011 !
#76000
b10000 "
b111101000001 $
b0 #
b10000 &
b11101 %
b1111010000011000000011101 !
#77000
b10100 "
b1100 $
b1 #
b1011 &
b11100 %
b11000101100111100 !
#78000
b10010 "
b100100001101 $
b110 #
b10001 &
b10001 %
b1001000011011000111010001 !
#79000
b11000 "
b110001100001 $
b11 #
b10010 &
b11 %
b1100011000011001001100011 !
#80000
b10001101000 $
b111 &
b10010 %
b100011010000011101110010 !
#81000
b10011 "
b111101001001 $
b111 #
b11110 &
b1001 %
b1111010010011111011101001 !
#82000
b10100 "
b10011 $
b1 #
b11011 &
b111 %
b100111101100100111 !
#83000
b10011 "
b111011101 $
b111 #
b1011 &
b10100 %
b1110111010101111110100 !
#84000
b10010 "
b100001000001 $
b110 #
b11111 &
b10011 %
b1000010000011111111010011 !
#85000
b10101 "
b11 $
b101 #
b10110 &
b1100 %
b111011010101100 !
#86000
b11000 "
b111101100011 $
b11 #
b100 &
b1 %
b1111011000110010001100001 !
#87000
b10001 "
b101011100110 $
b100 #
b11000 &
b101 %
b1010111001101100010000101 !
#88000
b10111 "
b111010100100 $
b10 #
b1 &
b10000 %
b1110101001000000101010000 !
#89000
b10010 "
b10111 $
b110 #
b11010 &
b11011 %
b101111101011011011 !
#90000
b10011001010 $
b10001 &
b111 %
b100110010101000111000111 !
#91000
b10111 "
b110100101010 $
b10 #
b10111 &
b10110 %
b1101001010101011101010110 !
#92000
b10100 "
b10000 $
b1 #
b11010 &
b11010 %
b100001101000111010 !
#93000
b10111 "
b10101001110 $
b10 #
b11111 &
b11 %
b101010011101111101000011 !
#94000
b10100 "
b11 $
b1 #
b1000 &
b10111 %
b110100000110111 !
#95000
b10010 "
b10100110111 $
b110 #
b11011 &
b1001 %
b101001101111101111001001 !
#96000
b10000 "
b1000000100 $
b0 #
b1011 &
b10 %
b10000001000101100000010 !
#97000
b110111111110 $
b101 &
b110 %
b1101111111100010100000110 !
#98000
b10100 "
b10000 $
b1 #
b11011 &
b11101 %
b100001101100111101 !
#99000
b0 "
b101111 $
b101 #
b10000 &
b11 %
b1011111000010100011 !
