ver/processor_defines.sv

// OPCODES
`define OP_REG 7'b011_0011
`define OP_IMM 7'b001_0011
`define OP_LOAD 7'b000_0011
`define OP_STORE  7'b010_0011
`define OP_BRANCH 7'b110_0011
`define OP_JAL 7'b110_1111
`define OP_JALR 7'b110_0111
`define OP_LUI 7'b011_0111
`define OP_AUIPC 7'b001_0111

// ALU Operations
`define ALU_NOP 5'd0
`define ADD 5'd1
`define SUB 5'd2
`define XOR 5'd3
`define OR 5'd4
`define AND 5'd5
`define SLL 5'd6
`define SRL 5'd7
`define SRA 5'd8
`define SLT 5'd9
`define SLTU 5'd10

`define ADDI 5'd16
`define XORI 5'd17
`define ORI 5'd18
`define ANDI 5'd19
`define SLLI 5'd20
`define SRLI 5'd21
`define SRAI 5'd22
`define SLTI 5'd23
`define SLTIU 5'd24

`define LUI 5'd28
`define AUIPC 5'd29

// BRANCH Operations
`define BR_NOP 3'd0
`define BEQ 3'd1
`define BNE 3'd2
`define BLT 3'd3
`define BGE 3'd4
`define BLTU 3'd5
`define BGEU 3'd6

// JUMP Operations
`define JMP_NOP 2'd0
`define JAL 2'd1
`define JALR 2'd2

// LOAD Operations
`define LD_NOP 3'd0
`define LB 3'd1
`define LH 3'd2
`define LW 3'd3
`define LBU 3'd4
`define LHU 3'd5

// STORE Operations
`define STR_NOP 3'd0
`define SB 3'd1
`define SH 3'd2
`define SW 3'd3

// LOAD - STATE MACHINES
`define LOAD_RESET 1'b0
`define READ_MEM 1'b1

// STORE - STATE MACHINES
`define STORE_RESET 1'b0
`define WRITE_MEM 1'b1

// MEM Addr Width
`define MEM_ADDR_WD 10

// FILE Included
`define FILE_INCL 1

ver/decode_upperimm_inst.sv
`ifndef FILE_INCL
    `include "processor_defines.sv"
`endif

module decode_upperimm_inst(
    input logic [31:0] instruction_code,
    output logic [4:0] rd,
    output logic [31:0] imm,
    output logic [4:0] alu_control
);
// always@(*) begin
//     rd = instruction_code[11:7];
//     imm[31:12] = instruction_code[31:12];
//     if(instruction_code[6:0] == 7'b0110111) begin
//         alu_control = `LUI;
//     end
//     else if(instruction_code[6:0] == 7'b0010111) begin
//         alu_control = `AUIPC;
//     end
// end
logic [6:0] opcode ;
always_comb begin 
    rd = instruction_code[11:7];
    imm[31:12] = instruction_code[31:12];
    opcode=instruction_code[6:0];

    for(int i = 11; i>= 0; i = i-1)
    begin
        imm[i] = 1'b0;

    end
    case(opcode)
    7'd55 : alu_control =`LUI;
    7'd23 : alu_control =`AUIPC;
    
    default : alu_control = `ALU_NOP;
    endcase
    
end


`ifndef SUBMODULE_DISABLE_WAVES
   initial
     begin
        $dumpfile("./sim_build/decode_upperimm_inst.vcd");
        $dumpvars(0, decode_upperimm_inst);
     end
 `endif
endmodule

sim_submodules/sim_build/decode_upperimm_inst.vcd
$date
	Sun Jul  7 22:20:45 2024
$end
$version
	Icarus Verilog
$end
$timescale
	1ps
$end
$scope module decode_upperimm_inst $end
$var wire 32 ! instruction_code [31:0] $end
$var reg 5 " alu_control [4:0] $end
$var reg 32 # imm [31:0] $end
$var reg 7 $ opcode [6:0] $end
$var reg 5 % rd [4:0] $end
$scope begin $ivl_for_loop0 $end
$var integer 32 & i [31:0] $end
$upscope $end
$upscope $end
$enddefinitions $end
#0
$dumpvars
b11111111111111111111111111111111 &
b11000 %
b0 $
b11011101010000100011000000000000 #
b0 "
b11011101010000100011110000000000 !
$end
#1000
b11111111111111111111111111111111 &
b11001 $
b1000000001101111111000000000000 #
b111 %
b1000000001101111111001110011001 !
#2000
b11111111111111111111111111111111 &
b10010101010010110000000000000 #
b1110 %
b10010101010010110011100011001 !
#3000
b11111111111111111111111111111111 &
b0 $
b1100001011101000110000000000000 #
b1010 %
b1100001011101000110010100000000 !
#4000
b11111111111111111111111111111111 &
b111101001010011101000000000000 #
b11101 %
b111101001010011101111010000000 !
#5000
b11111111111111111111111111111111 &
b11001 $
b10111011001000001010000000000000 #
b10001 %
b10111011001000001010100010011001 !
#6000
b11111111111111111111111111111111 &
b10101001101101100011000000000000 #
b1 %
b10101001101101100011000010011001 !
#7000
b11111111111111111111111111111111 &
b10001110010101011011000000000000 #
b1100 %
b10001110010101011011011000011001 !
#8000
b11100 "
b11111111111111111111111111111111 &
b110111 $
b1000111000000011010000000000000 #
b10010 %
b1000111000000011010100100110111 !
#9000
b0 "
b11111111111111111111111111111111 &
b0 $
b10100110110110110110000000000000 #
b111 %
b10100110110110110110001110000000 !
#10000
b11111111111111111111111111111111 &
b10101001110111110111000000000000 #
b11110 %
b10101001110111110111111100000000 !
#11000
b11100 "
b11111111111111111111111111111111 &
b110111 $
b1111100001100011000000000000 #
b10101 %
b1111100001100011101010110111 !
#12000
b0 "
b11111111111111111111111111111111 &
b0 $
b10000100111000010001000000000000 #
b101 %
b10000100111000010001001010000000 !
#13000
b11111111111111111111111111111111 &
b11001 $
b1111110001010101000000000000 #
b11110 %
b1111110001010101111100011001 !
#14000
b11111111111111111111111111111111 &
b10011100111110110000000000000000 #
b10 %
b10011100111110110000000100011001 !
#15000
b11111111111111111111111111111111 &
b100011100101100000000000000000 #
b11111 %
b100011100101100000111110011001 !
#16000
b11111111111111111111111111111111 &
b11010100000111110100000000000000 #
b11100 %
b11010100000111110100111000011001 !
#17000
b11100 "
b11111111111111111111111111111111 &
b110111 $
b11011000011000101010000000000000 #
b10010 %
b11011000011000101010100100110111 !
#18000
b0 "
b11111111111111111111111111111111 &
b11001 $
b10101010011011011000000000000 #
b1110 %
b10101010011011011011100011001 !
#19000
b11100 "
b11111111111111111111111111111111 &
b110111 $
b11010010001001000001000000000000 #
b11 %
b11010010001001000001000110110111 !
#20000
b0 "
b11111111111111111111111111111111 &
b0 $
b1011100111111000100000000000000 #
b10001 %
b1011100111111000100100010000000 !
#21000
b11100 "
b11111111111111111111111111111111 &
b110111 $
b10000110000111011011000000000000 #
b10011 %
b10000110000111011011100110110111 !
#22000
b0 "
b11111111111111111111111111111111 &
b0 $
b111010001111111100000000000000 #
b11110 %
b111010001111111100111100000000 !
#23000
b11100 "
b11111111111111111111111111111111 &
b110111 $
b11101000110100011100000000000000 #
b1010 %
b11101000110100011100010100110111 !
#24000
b11111111111111111111111111111111 &
b11000001010101011000000000000 #
b10111 %
b11000001010101011101110110111 !
#25000
b0 "
b11111111111111111111111111111111 &
b11001 $
b1010000000011100011000000000000 #
b11010 %
b1010000000011100011110100011001 !
#26000
b11111111111111111111111111111111 &
b0 $
b10100000101101001000000000000000 #
b1010 %
b10100000101101001000010100000000 !
#27000
b11111111111111111111111111111111 &
b11000001011000101001000000000000 #
b11000 %
b11000001011000101001110000000000 !
#28000
b11100 "
b11111111111111111111111111111111 &
b110111 $
b11100001011010101111000000000000 #
b1 %
b11100001011010101111000010110111 !
#29000
b0 "
b11111111111111111111111111111111 &
b11001 $
b1110100110000001100000000000000 #
b11011 %
b1110100110000001100110110011001 !
#30000
b11111111111111111111111111111111 &
b111101000010001000000000000 #
b11110 %
b111101000010001111100011001 !
#31000
b11111111111111111111111111111111 &
b0 $
b11110011000001100100000000000000 #
b1111 %
b11110011000001100100011110000000 !
#32000
b11111111111111111111111111111111 &
b11100000110010000111000000000000 #
b10110 %
b11100000110010000111101100000000 !
#33000
b11100 "
b11111111111111111111111111111111 &
b110111 $
b10010000011110001000000000000000 #
b10011 %
b10010000011110001000100110110111 !
#34000
b0 "
b11111111111111111111111111111111 &
b11001 $
b1110001011100100101000000000000 #
b10101 %
b1110001011100100101101010011001 !
#35000
b11100 "
b11111111111111111111111111111111 &
b110111 $
b111011011001000111000000000000 #
b1001 %
b111011011001000111010010110111 !
#36000
b11111111111111111111111111111111 &
b11110101011111001111000000000000 #
b101 %
b11110101011111001111001010110111 !
#37000
b11111111111111111111111111111111 &
b1000010110101000001000000000000 #
b110 %
b1000010110101000001001100110111 !
#38000
b0 "
b11111111111111111111111111111111 &
b11001 $
b1111100011100100011000000000000 #
b11 %
b1111100011100100011000110011001 !
#39000
b11111111111111111111111111111111 &
b1111101111111011111000000000000 #
b11101 %
b1111101111111011111111010011001 !
#40000
b11111111111111111111111111111111 &
b10110111111100011001000000000000 #
b1110 %
b10110111111100011001011100011001 !
#41000
b11111111111111111111111111111111 &
b10110111111011010000000000000 #
b11111 %
b10110111111011010111110011001 !
#42000
b11111111111111111111111111111111 &
b100010010011000100000000000000 #
b1100 %
b100010010011000100011000011001 !
#43000
b11111111111111111111111111111111 &
b1101011111001100000000000000 #
b11100 %
b1101011111001100111000011001 !
#44000
b11111111111111111111111111111111 &
b0 $
b10000101111010111111000000000000 #
b11011 %
b10000101111010111111110110000000 !
#45000
b11100 "
b11111111111111111111111111111111 &
b110111 $
b100101001010011000000000000000 #
b10101 %
b100101001010011000101010110111 !
#46000
b0 "
b11111111111111111111111111111111 &
b11001 $
b1110000010100000000000000 #
b100 %
b1110000010100001000011001 !
#47000
b11111111111111111111111111111111 &
b10000101101000000000000 #
b11000 %
b10000101101110000011001 !
#48000
b11100 "
b11111111111111111111111111111111 &
b110111 $
b1111010101000001011000000000000 #
b10000 %
b1111010101000001011100000110111 !
#49000
b11111111111111111111111111111111 &
b10110010011110011100000000000000 #
b11 %
b10110010011110011100000110110111 !
#50000
b11111111111111111111111111111111 &
b10101100010010001011000000000000 #
b11001 %
b10101100010010001011110010110111 !
#51000
b11111111111111111111111111111111 &
b101001101101011010000000000000 #
b10 %
b101001101101011010000100110111 !
#52000
b0 "
b11111111111111111111111111111111 &
b11001 $
b11100110011110001110000000000000 #
b110 %
b11100110011110001110001100011001 !
#53000
b11111111111111111111111111111111 &
b0 $
b11111101011111100011000000000000 #
b101 %
b11111101011111100011001010000000 !
#54000
b11100 "
b11111111111111111111111111111111 &
b110111 $
b1100100000100100000000000000000 #
b10010 %
b1100100000100100000100100110111 !
#55000
b0 "
b11111111111111111111111111111111 &
b0 $
b10111010100101001000000000000000 #
b1000 %
b10111010100101001000010000000000 !
#56000
b11111111111111111111111111111111 &
b11001 $
b11101101110011100000000000000 #
b11100 %
b11101101110011100111000011001 !
#57000
b11100 "
b11111111111111111111111111111111 &
b110111 $
b110000101011000000000000000 #
b10100 %
b110000101011000101000110111 !
#58000
b0 "
b11111111111111111111111111111111 &
b11001 $
b100100010111010010000000000000 #
b1 %
b100100010111010010000010011001 !
#59000
b11100 "
b11111111111111111111111111111111 &
b110111 $
b11111110000010000100000000000000 #
b10011 %
b11111110000010000100100110110111 !
#60000
b0 "
b11111111111111111111111111111111 &
b11001 $
b11001011011110011001000000000000 #
b11001011011110011001100110011001 !
#61000
b11100 "
b11111111111111111111111111111111 &
b110111 $
b10011000100011000100000000000000 #
b11101 %
b10011000100011000100111010110111 !
#62000
b0 "
b11111111111111111111111111111111 &
b11001 $
b10101101000101010110000000000000 #
b10111 %
b10101101000101010110101110011001 !
#63000
b11100 "
b11111111111111111111111111111111 &
b110111 $
b10010101101111011111000000000000 #
b11001 %
b10010101101111011111110010110111 !
#64000
b0 "
b11111111111111111111111111111111 &
b11001 $
b100011111011000000000000000000 #
b11 %
b100011111011000000000110011001 !
#65000
b11111111111111111111111111111111 &
b101001100111100011000000000000 #
b1001 %
b101001100111100011010010011001 !
#66000
b11111111111111111111111111111111 &
b11001110101100110001000000000000 #
b11101 %
b11001110101100110001111010011001 !
#67000
b11111111111111111111111111111111 &
b1011011001100101110000000000000 #
b11011 %
b1011011001100101110110110011001 !
#68000
b11100 "
b11111111111111111111111111111111 &
b110111 $
b110001001001110000000000000 #
b10011 %
b110001001001110100110110111 !
#69000
b0 "
b11111111111111111111111111111111 &
b0 $
b10000000000011010000000000000000 #
b11010 %
b10000000000011010000110100000000 !
#70000
b11111111111111111111111111111111 &
b11100110011001011000000000000 #
b10100 %
b11100110011001011101000000000 !
#71000
b11100 "
b11111111111111111111111111111111 &
b110111 $
b1011011011101000000000000000 #
b11111 %
b1011011011101000111110110111 !
#72000
b0 "
b11111111111111111111111111111111 &
b11001 $
b1101100100000000111000000000000 #
b10100 %
b1101100100000000111101000011001 !
#73000
b11111111111111111111111111111111 &
b0 $
b10111010101000111000000000000000 #
b10011 %
b10111010101000111000100110000000 !
#74000
b11100 "
b11111111111111111111111111111111 &
b110111 $
b110101100011001000000000000000 #
b1011 %
b110101100011001000010110110111 !
#75000
b11111111111111111111111111111111 &
b1110001000111101110000000000000 #
b10010 %
b1110001000111101110100100110111 !
#76000
b11111111111111111111111111111111 &
b1100100001001000000000000000 #
b10011 %
b1100100001001000100110110111 !
#77000
b0 "
b11111111111111111111111111111111 &
b0 $
b101110100100110010000000000000 #
b10100 %
b101110100100110010101000000000 !
#78000
b11111111111111111111111111111111 &
b1011001010001110011000000000000 #
b110 %
b1011001010001110011001100000000 !
#79000
b11111111111111111111111111111111 &
b11001 $
b11001011110111111100000000000000 #
b11100 %
b11001011110111111100111000011001 !
#80000
b11111111111111111111111111111111 &
b11100101111101101000000000000000 #
b10101 %
b11100101111101101000101010011001 !
#81000
b11111111111111111111111111111111 &
b111100110000000010000000000000 #
b111100110000000010101010011001 !
#82000
b11111111111111111111111111111111 &
b1011101000100001001000000000000 #
b110 %
b1011101000100001001001100011001 !
#83000
b11111111111111111111111111111111 &
b10101101011111011000000000000 #
b10 %
b10101101011111011000100011001 !
#84000
b11111111111111111111111111111111 &
b10011111010101110100000000000000 #
b11100 %
b10011111010101110100111000011001 !
#85000
b11111111111111111111111111111111 &
b1001101010001000110000000000000 #
b10101 %
b1001101010001000110101010011001 !
#86000
b11111111111111111111111111111111 &
b0 $
b11010110001100110010000000000000 #
b1000 %
b11010110001100110010010000000000 !
#87000
b11111111111111111111111111111111 &
b110111011101000000000000000000 #
b11011 %
b110111011101000000110110000000 !
#88000
b11111111111111111111111111111111 &
b11001 $
b10011000001001101110000000000000 #
b110 %
b10011000001001101110001100011001 !
#89000
b11111111111111111111111111111111 &
b0 $
b10011100111100110000000000000000 #
b11011 %
b10011100111100110000110110000000 !
#90000
b11111111111111111111111111111111 &
b11001 $
b1000001111011001011000000000000 #
b11001 %
b1000001111011001011110010011001 !
#91000
b11111111111111111111111111111111 &
b0 $
b1000110101100011101000000000000 #
b11 %
b1000110101100011101000110000000 !
#92000
b11111111111111111111111111111111 &
b11001 $
b10100110001111101011000000000000 #
b11000 %
b10100110001111101011110000011001 !
#93000
b11111111111111111111111111111111 &
b0 $
b10011000010011011100000000000000 #
b11001 %
b10011000010011011100110010000000 !
#94000
b11111111111111111111111111111111 &
b1011101000010001010000000000000 #
b10 %
b1011101000010001010000100000000 !
#95000
b11100 "
b11111111111111111111111111111111 &
b110111 $
b1011010001010001101000000000000 #
b1111 %
b1011010001010001101011110110111 !
#96000
b0 "
b11111111111111111111111111111111 &
b11001 $
b11101100110010110000000000000 #
b1001 %
b11101100110010110010010011001 !
#97000
b11111111111111111111111111111111 &
b11001101010110110000000000000000 #
b11 %
b11001101010110110000000110011001 !
#98000
b11100 "
b11111111111111111111111111111111 &
b110111 $
b11010001100100111110000000000000 #
b11010 %
b11010001100100111110110100110111 !
#99000
b0 "
b11111111111111111111111111111111 &
b0 $
b1101010111001000000000000000 #
b10110 %
b1101010111001000101100000000 !
