ver/processor_defines.sv

// OPCODES
`define OP_REG 7'b011_0011
`define OP_IMM 7'b001_0011
`define OP_LOAD 7'b000_0011
`define OP_STORE  7'b010_0011
`define OP_BRANCH 7'b110_0011
`define OP_JAL 7'b110_1111
`define OP_JALR 7'b110_0111
`define OP_LUI 7'b011_0111
`define OP_AUIPC 7'b001_0111

// ALU Operations
`define ALU_NOP 5'd0
`define ADD 5'd1
`define SUB 5'd2
`define XOR 5'd3
`define OR 5'd4
`define AND 5'd5
`define SLL 5'd6
`define SRL 5'd7
`define SRA 5'd8
`define SLT 5'd9
`define SLTU 5'd10

`define ADDI 5'd16
`define XORI 5'd17
`define ORI 5'd18
`define ANDI 5'd19
`define SLLI 5'd20
`define SRLI 5'd21
`define SRAI 5'd22
`define SLTI 5'd23
`define SLTIU 5'd24

`define LUI 5'd28
`define AUIPC 5'd29

// BRANCH Operations
`define BR_NOP 3'd0
`define BEQ 3'd1
`define BNE 3'd2
`define BLT 3'd3
`define BGE 3'd4
`define BLTU 3'd5
`define BGEU 3'd6

// JUMP Operations
`define JMP_NOP 2'd0
`define JAL 2'd1
`define JALR 2'd2

// LOAD Operations
`define LD_NOP 3'd0
`define LB 3'd1
`define LH 3'd2
`define LW 3'd3
`define LBU 3'd4
`define LHU 3'd5

// STORE Operations
`define STR_NOP 3'd0
`define SB 3'd1
`define SH 3'd2
`define SW 3'd3

// LOAD - STATE MACHINES
`define LOAD_RESET 1'b0
`define READ_MEM 1'b1

// STORE - STATE MACHINES
`define STORE_RESET 1'b0
`define WRITE_MEM 1'b1

// MEM Addr Width
`define MEM_ADDR_WD 10

// FILE Included
`define FILE_INCL 1

ver/load.sv

`ifndef FILE_INCL
    `include "processor_defines.sv"
`endif


module load(
    input logic i_clk,
    input logic i_rst,
    input logic [31:0] rs1_val,
    input logic [31:0] imm,
    input logic [31:0] mem_data,
    input logic [4:0] rd_in,
    input logic [2:0] load_control,
    output logic stall_pc,
    output logic ignore_curr_inst,
    output logic rd_write_control,
    output logic [4:0] rd_out,
    output logic [31:0] rd_write_val,
    output logic mem_rw_mode,
    output logic [31:0] mem_addr
);
    parameter RESET_STATE = 0;
    parameter READ_MEM=1;
    logic state;
    logic next_state;
    logic [2:0] load_control_s;
    logic [4:0] rd_s;
    logic [31:0]mem_addr_s;

    assign mem_rw_mode =1'b1;

    always@(posedge i_clk or negedge i_rst) begin

        if(~i_rst) begin
            state <= 'b0;
            load_control_s<= 'b0;
            rd_s <= 'b0;
            mem_addr_s<='b0;
        end
        else begin
            load_control_s<= load_control;
            rd_s <= rd_in;
            state <= next_state; 
            mem_addr_s<= mem_addr;
        end

    end

    always@(*) begin
            case(state) 
            RESET_STATE: begin
                ignore_curr_inst='b0;
                rd_write_control='b0;
                rd_write_val='b0;
                rd_out='b0;
                if(|load_control) begin
                    mem_addr= imm+ rs1_val;
                    stall_pc='b1; 
                    next_state = READ_MEM;
                    end
                else begin
                next_state = RESET_STATE;
                stall_pc='b0;
                mem_addr='b0;
                ignore_curr_inst='b0;
                rd_write_control='b0;
                rd_write_val='b0;
                end
            end
            

            READ_MEM: begin
                case(load_control_s)

                `LD_NOP: begin 
                    rd_write_control='b0;
                    rd_write_val='b0; end

                `LB: begin
                    rd_write_control=1'b1;
                    if(mem_addr_s[1:0]==2'b00)
                    rd_write_val= {{24{mem_data[7]}},mem_data[7:0]};
                    else if(mem_addr_s[1:0]==2'b01)
                    rd_write_val= {{24{mem_data[15]}},mem_data[15:8]};
                    else if(mem_addr_s[1:0]==2'b10)
                    rd_write_val= {{24{mem_data[23]}},mem_data[23:16]};
                    else
                    rd_write_val= {{24{mem_data[31]}},mem_data[31:24]};
                     end

                `LH:begin
                    rd_write_control='b1;
                    if(mem_addr_s[1]==0)
                    rd_write_val= {{16{mem_data[15]}},mem_data[15:0]};
                    else 
                    rd_write_val= {{16{mem_data[31]}},mem_data[31:16]};
                    end

                `LW:begin
                    rd_write_val = mem_data;
                    rd_write_control=1'b1;
                    end
                    
                `LBU:begin
                    rd_write_control=1'b1;
                    if(mem_addr_s[1:0]==2'b00)
                    rd_write_val= {24'b0,mem_data[7:0]};
                    else if(mem_addr_s[1:0]==2'b01)
                    rd_write_val= {24'b0,mem_data[15:8]};
                    else if(mem_addr_s[1:0]==2'b10)
                    rd_write_val= {24'b0,mem_data[23:16]};
                    else
                    rd_write_val= {24'b0,mem_data[31:24]};
                     end
                `LHU:begin
                    rd_write_control=1'b1;
                    if(mem_addr_s[1]==0)
                    rd_write_val= {16'b0,mem_data[15:0]};
                    else 
                    rd_write_val= {16'b0,mem_data[31:16]};
                     end
                endcase

                stall_pc=1'b0;
                ignore_curr_inst='b1;
                rd_out= rd_s;
                next_state = RESET_STATE;
                mem_addr='b0;
            end

            endcase
    end
`ifndef SUBMODULE_DISABLE_WAVES
   initial
     begin
        $dumpfile("./sim_build/load.vcd");
        $dumpvars(0, load);
     end
 `endif

endmodule

sim_submodules/sim_build/load.vcd
$date
	Sun Jul  7 23:03:51 2024
$end
$version
	Icarus Verilog
$end
$timescale
	1ps
$end
$scope module load $end
$var wire 1 ! i_clk $end
$var wire 1 " i_rst $end
$var wire 32 # imm [31:0] $end
$var wire 3 $ load_control [2:0] $end
$var wire 32 % mem_data [31:0] $end
$var wire 1 & mem_rw_mode $end
$var wire 5 ' rd_in [4:0] $end
$var wire 32 ( rs1_val [31:0] $end
$var reg 1 ) ignore_curr_inst $end
$var reg 3 * load_control_s [2:0] $end
$var reg 32 + mem_addr [31:0] $end
$var reg 32 , mem_addr_s [31:0] $end
$var reg 1 - next_state $end
$var reg 5 . rd_out [4:0] $end
$var reg 5 / rd_s [4:0] $end
$var reg 1 0 rd_write_control $end
$var reg 32 1 rd_write_val [31:0] $end
$var reg 1 2 stall_pc $end
$var reg 1 3 state $end
$upscope $end
$enddefinitions $end
#0
$dumpvars
x3
x2
bx 1
x0
bx /
bx .
x-
bx ,
bx +
bx *
x)
b0 (
b0 '
1&
b0 %
b0 $
b0 #
1"
0!
$end
#5000
b0 /
b0 *
1!
#5500
b0 +
02
0-
b0 .
b0 1
00
0)
b0 ,
03
0"
0!
#6000
1!
#6500
0!
#7000
1"
1!
#7500
0!
#8000
1!
#8100
1-
12
b101000101110110011111100011 +
b100 $
b1101 '
b110101000 #
b101000101110110011000111011 (
#8500
0!
#9000
b10110000 1
b0 #
b0 (
b0 '
b0 $
b10110000110000001000011001100101 %
b0 +
0-
b1101 .
1)
02
10
b101000101110110011111100011 ,
13
b1101 /
b100 *
1!
#9500
0!
#10000
b0 .
b0 1
00
0)
b0 ,
03
b0 /
b0 *
1!
#10100
1-
12
b111010010111100101001011011000 +
b1 $
b1000 '
b0 %
b101101101101 #
b111010010111100100011101101011 (
#10500
0!
#11000
b1100101 1
b0 #
b0 (
b0 '
b0 $
b10100011110101100111001101100101 %
b0 +
0-
b1000 .
1)
02
10
b111010010111100101001011011000 ,
13
b1000 /
b1 *
1!
#11500
0!
#12000
b0 .
b0 1
00
0)
b0 ,
03
b0 /
b0 *
1!
#12100
1-
12
b10111001001001010011101000111 +
b100 $
b1 '
b0 %
b1011010011 #
b10111001001001010010001110100 (
#12500
0!
#13000
b1000010 1
b0 #
b0 (
b0 '
b0 $
b1000010000000110101011101110100 %
b0 +
0-
b1 .
1)
02
10
b10111001001001010011101000111 ,
13
b1 /
b100 *
1!
#13500
0!
#14000
b0 .
b0 1
00
0)
b0 ,
03
b0 /
b0 *
1!
#14100
1-
12
b10010011010011001100100110011 +
b11 $
b1100 '
b0 %
b1011100111 #
b10010011010011001011001001100 (
#14500
0!
#15000
b1101000101010111101111111011100 1
b0 #
b0 (
b0 '
b0 $
b1101000101010111101111111011100 %
b0 +
0-
b1100 .
1)
02
10
b10010011010011001100100110011 ,
13
b1100 /
b11 *
1!
#15500
0!
#16000
b0 .
b0 1
00
0)
b0 ,
03
b0 /
b0 *
1!
#16100
1-
12
b1001100010000010101111101111 +
b1 $
b11011 '
b0 %
b110010010110 #
b1001100010000001111101011001 (
#16500
0!
#17000
b1101 1
b0 #
b0 (
b0 '
b0 $
b1101110000101101000001011001 %
b0 +
0-
b11011 .
1)
02
10
b1001100010000010101111101111 ,
13
b11011 /
b1 *
1!
#17500
0!
#18000
b0 .
b0 1
00
0)
b0 ,
03
b0 /
b0 *
1!
#18100
b1010 '
b0 %
b101100000001 #
b10110000001100001100010000001 (
#18500
0!
#19000
b1010 /
1!
#19100
1-
12
b1110111011010010101111110011 +
b10 $
b1100 '
b100110000 #
b1110111011010010101011000011 (
#19500
0!
#20000
b111101100101000 1
b0 #
b0 (
b0 '
b0 $
b1111011001010001110110110111000 %
b0 +
0-
b1100 .
1)
02
10
b1110111011010010101111110011 ,
13
b1100 /
b10 *
1!
#20500
0!
#21000
b0 .
b0 1
00
0)
b0 ,
03
b0 /
b0 *
1!
#21100
1-
12
b101101111101110001000001100000 +
b11 $
b10011 '
b0 %
b11011101111 #
b101101111101110000100101110001 (
#21500
0!
#22000
b1010000011011101001011100001001 1
b0 #
b0 (
b0 '
b0 $
b1010000011011101001011100001001 %
b0 +
0-
b10011 .
1)
02
10
b101101111101110001000001100000 ,
13
b10011 /
b11 *
1!
#22500
0!
#23000
b0 .
b0 1
00
0)
b0 ,
03
b0 /
b0 *
1!
#23100
1-
12
b101010101101010001101110100010 +
b10 $
b1111 '
b0 %
b110101111011 #
b101010101101010000111000100111 (
#23500
0!
#24000
b110100000110110 1
b0 #
b0 (
b0 '
b0 $
b1101000001101101000010101010001 %
b0 +
0-
b1111 .
1)
02
10
b101010101101010001101110100010 ,
13
b1111 /
b10 *
1!
#24500
0!
#25000
b0 .
b0 1
00
0)
b0 ,
03
b0 /
b0 *
1!
#25100
1-
12
b110100111101000101011101011100 +
b101 $
b10 '
b0 %
b101100010000 #
b110100111101000100110001001100 (
#25500
0!
#26000
b1110010000011100 1
b0 #
b0 (
b0 '
b0 $
b10010001101100111110010000011100 %
b0 +
0-
b10 .
1)
02
10
b110100111101000101011101011100 ,
13
b10 /
b101 *
1!
#26500
0!
#27000
b0 .
b0 1
00
0)
b0 ,
03
b0 /
b0 *
1!
#27100
1-
12
b100111010101011111000010111111 +
b1 $
b1010 '
b0 %
b1010010111 #
b100111010101011110111000101000 (
#27500
0!
#28000
b11111111111111111111111111011010 1
b0 #
b0 (
b0 '
b0 $
b11011010011000110101100101100110 %
b0 +
0-
b1010 .
1)
02
10
b100111010101011111000010111111 ,
13
b1010 /
b1 *
1!
#28500
0!
#29000
b0 .
b0 1
00
0)
b0 ,
03
b0 /
b0 *
1!
#29100
b11011 '
b0 %
b100001101001 #
b1000000011001010010111111000 (
#29500
0!
#30000
b11011 /
1!
#30100
1-
12
b11010100111101100011011110111 +
b1 $
b0 '
b110110010010 #
b11010100111101011100101100101 (
#30500
0!
#31000
b11111111111111111111111110100111 1
b0 #
b0 (
b0 $
b10100111110110101011111011000000 %
b0 +
0-
1)
02
10
b11010100111101100011011110111 ,
13
b0 /
b1 *
1!
#31500
0!
#32000
b0 1
00
0)
b0 ,
03
b0 *
1!
#32100
1-
12
b1001110010110000001111110111 +
b100 $
b11101 '
b0 %
b100011101010 #
b1001110010101111101100001101 (
#32500
0!
#33000
b1100110 1
b0 #
b0 (
b0 '
b0 $
b1100110100101000101111010010001 %
b0 +
0-
b11101 .
1)
02
10
b1001110010110000001111110111 ,
13
b11101 /
b100 *
1!
#33500
0!
#34000
b0 .
b0 1
00
0)
b0 ,
03
b0 /
b0 *
1!
#34100
1-
12
b100111110100100011100010011110 +
b100 $
b1111 '
b0 %
b110110011100 #
b100111110100100010101100000010 (
#34500
0!
#35000
b10011110 1
b0 #
b0 (
b0 '
b0 $
b1100100111101011110101011110 %
b0 +
0-
b1111 .
1)
02
10
b100111110100100011100010011110 ,
13
b1111 /
b100 *
1!
#35500
0!
#36000
b0 .
b0 1
00
0)
b0 ,
03
b0 /
b0 *
1!
#36100
1-
12
b101010011111110010010100001100 +
b100 $
b100 '
b0 %
b111110010000 #
b101010011111110001010101111100 (
#36500
0!
#37000
b11110001 1
b0 #
b0 (
b0 '
b0 $
b10010011010101110010000111110001 %
b0 +
0-
b100 .
1)
02
10
b101010011111110010010100001100 ,
13
b100 /
b100 *
1!
#37500
0!
#38000
b0 .
b0 1
00
0)
b0 ,
03
b0 /
b0 *
1!
#38100
1-
12
b1010101100111111111100011111 +
b101 $
b10011 '
b0 %
b111010110 #
b1010101100111111110101001001 (
#38500
0!
#39000
b1110111010000 1
b0 #
b0 (
b0 '
b0 $
b11101110100001001110100000101 %
b0 +
0-
b10011 .
1)
02
10
b1010101100111111111100011111 ,
13
b10011 /
b101 *
1!
#39500
0!
#40000
b0 .
b0 1
00
0)
b0 ,
03
b0 /
b0 *
1!
#40100
1-
12
b111110101111100011100100101100 +
b10 $
b11110 '
b0 %
b11001111111 #
b111110101111100011001010101101 (
#40500
0!
#41000
b111000100100110 1
b0 #
b0 (
b0 '
b0 $
b11110100011101100111000100100110 %
b0 +
0-
b11110 .
1)
02
10
b111110101111100011100100101100 ,
13
b11110 /
b10 *
1!
#41500
0!
#42000
b0 .
b0 1
00
0)
b0 ,
03
b0 /
b0 *
1!
#42100
1-
12
b1101000010100111101011011100 +
b1 $
b1101 '
b0 %
b110101100101 #
b1101000010100110110101110111 (
#42500
0!
#43000
b111110 1
b0 #
b0 (
b0 '
b0 $
b11111111110110000100010100111110 %
b0 +
0-
b1101 .
1)
02
10
b1101000010100111101011011100 ,
13
b1101 /
b1 *
1!
#43500
0!
#44000
b0 .
b0 1
00
0)
b0 ,
03
b0 /
b0 *
1!
#44100
1-
12
b110001100110111000111001001111 +
b100 $
b1 '
b0 %
b100101101110 #
b110001100110111000010011100001 (
#44500
0!
#45000
b111100 1
b0 #
b0 (
b0 '
b0 $
b111100111111001001100001010000 %
b0 +
0-
b1 .
1)
02
10
b110001100110111000111001001111 ,
13
b1 /
b100 *
1!
#45500
0!
#46000
b0 .
b0 1
00
0)
b0 ,
03
b0 /
b0 *
1!
#46100
1-
12
b110011010001101000100011111 +
b100 $
b1011 '
b0 %
b100111001010 #
b110011010001100011101010101 (
#46500
0!
#47000
b1000000 1
b0 #
b0 (
b0 '
b0 $
b1000000000101011110001000100101 %
b0 +
0-
b1011 .
1)
02
10
b110011010001101000100011111 ,
13
b1011 /
b100 *
1!
#47500
0!
#48000
b0 .
b0 1
00
0)
b0 ,
03
b0 /
b0 *
1!
#48100
1-
12
b11111000110010111110110011 +
b1 $
b10001 '
b0 %
b101101010111 #
b11111000110010010001011100 (
#48500
0!
#49000
b11111111111111111111111111000011 1
b0 #
b0 (
b0 '
b0 $
b11000011000000000000011000001010 %
b0 +
0-
b10001 .
1)
02
10
b11111000110010111110110011 ,
13
b10001 /
b1 *
1!
#49500
0!
#50000
b0 .
b0 1
00
0)
b0 ,
03
b0 /
b0 *
1!
#50100
b1010 '
b0 %
b110011000111 #
b1000101011111100011000011011 (
#50500
0!
#51000
b1010 /
1!
#51100
b110 '
b11001001111 #
b10011101011001011010011010001 (
#51500
0!
#52000
b110 /
1!
#52100
1-
12
b1011001100010001100001100101 +
b100 $
b11110 '
b110110010100 #
b1011001100010000101011010001 (
#52500
0!
#53000
b11110101 1
b0 #
b0 (
b0 '
b0 $
b11111111011011111010110100001 %
b0 +
0-
b11110 .
1)
02
10
b1011001100010001100001100101 ,
13
b11110 /
b100 *
1!
#53500
0!
#54000
b0 .
b0 1
00
0)
b0 ,
03
b0 /
b0 *
1!
#54100
1-
12
b100101101001110101110010010110 +
b100 $
b11000 '
b0 %
b100100110 #
b100101101001110101101101110000 (
#54500
0!
#55000
b11101 1
b0 #
b0 (
b0 '
b0 $
b10011000111011110111010000110 %
b0 +
0-
b11000 .
1)
02
10
b100101101001110101110010010110 ,
13
b11000 /
b100 *
1!
#55500
0!
#56000
b0 .
b0 1
00
0)
b0 ,
03
b0 /
b0 *
1!
#56100
b10010 '
b0 %
b1001000010 #
b11100001000000110010010110101 (
#56500
0!
#57000
b10010 /
1!
#57100
1-
12
b111011011001000100100011101101 +
b101 $
b10011 '
b11000110000 #
b111011011001000100001010111101 (
#57500
0!
#58000
b101110110111110 1
b0 #
b0 (
b0 '
b0 $
b11000010101100110101110110111110 %
b0 +
0-
b10011 .
1)
02
10
b111011011001000100100011101101 ,
13
b10011 /
b101 *
1!
#58500
0!
#59000
b0 .
b0 1
00
0)
b0 ,
03
b0 /
b0 *
1!
#59100
1-
12
b111010000001000010111000010110 +
b101 $
b11010 '
b0 %
b110110001000 #
b111010000001000010000010001110 (
#59500
0!
#60000
b110010000101000 1
b0 #
b0 (
b0 '
b0 $
b1100100001010001010110111101000 %
b0 +
0-
b11010 .
1)
02
10
b111010000001000010111000010110 ,
13
b11010 /
b101 *
1!
#60500
0!
#61000
b0 .
b0 1
00
0)
b0 ,
03
b0 /
b0 *
1!
#61100
1-
12
b11101111000110001000111011111 +
b11 $
b11100 '
b0 %
b101010000000 #
b11101111000110000011101011111 (
#61500
0!
#62000
b10111011011011100100101010011100 1
b0 #
b0 (
b0 '
b0 $
b10111011011011100100101010011100 %
b0 +
0-
b11100 .
1)
02
10
b11101111000110001000111011111 ,
13
b11100 /
b11 *
1!
#62500
0!
#63000
b0 .
b0 1
00
0)
b0 ,
03
b0 /
b0 *
1!
#63100
1-
12
b111111001000011000001100110 +
b10 $
b110 '
b0 %
b1110111010 #
b111111001000010110010101100 (
#63500
0!
#64000
b101010101011100 1
b0 #
b0 (
b0 '
b0 $
b1010101010111001010110010110001 %
b0 +
0-
b110 .
1)
02
10
b111111001000011000001100110 ,
13
b110 /
b10 *
1!
#64500
0!
#65000
b0 .
b0 1
00
0)
b0 ,
03
b0 /
b0 *
1!
#65100
1-
12
b111100111000011011100010011010 +
b101 $
b11111 '
b0 %
b10000000011 #
b111100111000011011010010010111 (
#65500
0!
#66000
b110001101100101 1
b0 #
b0 (
b0 '
b0 $
b1100011011001010100110111110000 %
b0 +
0-
b11111 .
1)
02
10
b111100111000011011100010011010 ,
13
b11111 /
b101 *
1!
#66500
0!
#67000
b0 .
b0 1
00
0)
b0 ,
03
b0 /
b0 *
1!
#67100
1-
12
b110000010100011110010001110110 +
b1 $
b1010 '
b0 %
b100010000000 #
b110000010100011101101111110110 (
#67500
0!
#68000
b11111111111111111111111110101111 1
b0 #
b0 (
b0 '
b0 $
b100101101011111100000011111111 %
b0 +
0-
b1010 .
1)
02
10
b110000010100011110010001110110 ,
13
b1010 /
b1 *
1!
#68500
0!
#69000
b0 .
b0 1
00
0)
b0 ,
03
b0 /
b0 *
1!
#69100
1-
12
b110100101010011011101101011101 +
b101 $
b11101 '
b0 %
b110001011011 #
b110100101010011010111100000010 (
#69500
0!
#70000
b11100010011001 1
b0 #
b0 (
b0 '
b0 $
b1000111111101010011100010011001 %
b0 +
0-
b11101 .
1)
02
10
b110100101010011011101101011101 ,
13
b11101 /
b101 *
1!
#70500
0!
#71000
b0 .
b0 1
00
0)
b0 ,
03
b0 /
b0 *
1!
#71100
1-
12
b111100110110100100001010011100 +
b1 $
b10011 '
b0 %
b111010101110 #
b111100110110100011001111101110 (
#71500
0!
#72000
b1111101 1
b0 #
b0 (
b0 '
b0 $
b10110100110111101110110101111101 %
b0 +
0-
b10011 .
1)
02
10
b111100110110100100001010011100 ,
13
b10011 /
b1 *
1!
#72500
0!
#73000
b0 .
b0 1
00
0)
b0 ,
03
b0 /
b0 *
1!
#73100
1-
12
b11100100000001100001011111000 +
b101 $
b11101 '
b0 %
b110000101 #
b11100100000001100000101110011 (
#73500
0!
#74000
b1000000001011111 1
b0 #
b0 (
b0 '
b0 $
b101111111001000000001011111 %
b0 +
0-
b11101 .
1)
02
10
b11100100000001100001011111000 ,
13
b11101 /
b101 *
1!
#74500
0!
#75000
b0 .
b0 1
00
0)
b0 ,
03
b0 /
b0 *
1!
#75100
1-
12
b1111000010111001001100110 +
b10 $
b1011 '
b0 %
b1110000011 #
b1111000010110111011100011 (
#75500
0!
#76000
b1101011110111 1
b0 #
b0 (
b0 '
b0 $
b11010111101110010001101100010 %
b0 +
0-
b1011 .
1)
02
10
b1111000010111001001100110 ,
13
b1011 /
b10 *
1!
#76500
0!
#77000
b0 .
b0 1
00
0)
b0 ,
03
b0 /
b0 *
1!
#77100
1-
12
b101000010011110111000011111 +
b101 $
b11100 '
b0 %
b11010011 #
b101000010011110110101001100 (
#77500
0!
#78000
b1010010101000000 1
b0 #
b0 (
b0 '
b0 $
b10100101010000001001110010100100 %
b0 +
0-
b11100 .
1)
02
10
b101000010011110111000011111 ,
13
b11100 /
b101 *
1!
#78500
0!
#79000
b0 .
b0 1
00
0)
b0 ,
03
b0 /
b0 *
1!
#79100
1-
12
b100100101110111111101001000 +
b11 $
b10110 '
b0 %
b10000001 #
b100100101110111111011000111 (
#79500
0!
#80000
b1011001010111011001001100101111 1
b0 #
b0 (
b0 '
b0 $
b1011001010111011001001100101111 %
b0 +
0-
b10110 .
1)
02
10
b100100101110111111101001000 ,
13
b10110 /
b11 *
1!
#80500
0!
#81000
b0 .
b0 1
00
0)
b0 ,
03
b0 /
b0 *
1!
#81100
b11001 '
b0 %
b10111100011 #
b11101001100100101110101011 (
#81500
0!
#82000
b11001 /
1!
#82100
1-
12
b11010000010110011100110001011 +
b1 $
b11010 '
b110100110111 #
b11010000010110010110001010100 (
#82500
0!
#83000
b0 #
b0 (
b0 '
b0 $
b110101100100010110010010 %
b0 +
0-
b11010 .
1)
02
10
b11010000010110011100110001011 ,
13
b11010 /
b1 *
1!
#83500
0!
#84000
b0 .
00
0)
b0 ,
03
b0 /
b0 *
1!
#84100
1-
12
b11001000000100100001111110100 +
b1 $
b11001 '
b0 %
b100001011111 #
b11001000000100011101110010101 (
#84500
0!
#85000
b11111111111111111111111111101110 1
b0 #
b0 (
b0 '
b0 $
b10110100000111101100100011101110 %
b0 +
0-
b11001 .
1)
02
10
b11001000000100100001111110100 ,
13
b11001 /
b1 *
1!
#85500
0!
#86000
b0 .
b0 1
00
0)
b0 ,
03
b0 /
b0 *
1!
#86100
1-
12
b11011011001011110101101110110 +
b100 $
b11001 '
b0 %
b1100011001 #
b11011011001011110100001011101 (
#86500
0!
#87000
b1000011 1
b0 #
b0 (
b0 '
b0 $
b110010010000110000001011010111 %
b0 +
0-
b11001 .
1)
02
10
b11011011001011110101101110110 ,
13
b11001 /
b100 *
1!
#87500
0!
#88000
b0 .
b0 1
00
0)
b0 ,
03
b0 /
b0 *
1!
#88100
1-
12
b111100111100011011000000101000 +
b10 $
b11011 '
b0 %
b1110001011 #
b111100111100011010110010011101 (
#88500
0!
#89000
b1100000011010 1
b0 #
b0 (
b0 '
b0 $
b111111101001010001100000011010 %
b0 +
0-
b11011 .
1)
02
10
b111100111100011011000000101000 ,
13
b11011 /
b10 *
1!
#89500
0!
#90000
b0 .
b0 1
00
0)
b0 ,
03
b0 /
b0 *
1!
#90100
1-
12
b10010111010111011000110110100 +
b1 $
b1110 '
b0 %
b110101001010 #
b10010111010111010010001101010 (
#90500
0!
#91000
b11111111111111111111111110001100 1
b0 #
b0 (
b0 '
b0 $
b11001010001111011010101110001100 %
b0 +
0-
b1110 .
1)
02
10
b10010111010111011000110110100 ,
13
b1110 /
b1 *
1!
#91500
0!
#92000
b0 .
b0 1
00
0)
b0 ,
03
b0 /
b0 *
1!
#92100
1-
12
b100010010001001101100110101010 +
b100 $
b11010 '
b0 %
b1111001001 #
b100010010001001101010111100001 (
#92500
0!
#93000
b10100100 1
b0 #
b0 (
b0 '
b0 $
b1000001101001000001011101010011 %
b0 +
0-
b11010 .
1)
02
10
b100010010001001101100110101010 ,
13
b11010 /
b100 *
1!
#93500
0!
#94000
b0 .
b0 1
00
0)
b0 ,
03
b0 /
b0 *
1!
#94100
b11001 '
b0 %
b11110010100 #
b1010111010000110111000011000 (
#94500
0!
#95000
b11001 /
1!
#95100
1-
12
b10100100100100100001100001101 +
b11 $
b1100 '
b100000010101 #
b10100100100100011101011111000 (
#95500
0!
#96000
b10010100101000010011110111000101 1
b0 #
b0 (
b0 '
b0 $
b10010100101000010011110111000101 %
b0 +
0-
b1100 .
1)
02
10
b10100100100100100001100001101 ,
13
b1100 /
b11 *
1!
#96500
0!
#97000
b0 .
b0 1
00
0)
b0 ,
03
b0 /
b0 *
1!
#97100
1-
12
b10100110100000000101100001010 +
b101 $
b1 '
b0 %
b10011110110 #
b10100110100000000011000010100 (
#97500
0!
#98000
b1000110100111011 1
b0 #
b0 (
b0 '
b0 $
b10001101001110110110010001011011 %
b0 +
0-
b1 .
1)
02
10
b10100110100000000101100001010 ,
13
b1 /
b101 *
1!
#98500
0!
#99000
b0 .
b0 1
00
0)
b0 ,
03
b0 /
b0 *
1!
#99100
1-
12
b10110011110101111100101010001 +
b101 $
b111 '
b0 %
b10011 #
b10110011110101111100100111110 (
#99500
0!
#100000
b110101100100001 1
b0 #
b0 (
b0 '
b0 $
b1110000111001100110101100100001 %
b0 +
0-
b111 .
1)
02
10
b10110011110101111100101010001 ,
13
b111 /
b101 *
1!
#100500
0!
#101000
b0 .
b0 1
00
0)
b0 ,
03
b0 /
b0 *
1!
#101100
1-
12
b110110010011101001000011100110 +
b10 $
b11100 '
b0 %
b101000011010 #
b110110010011101000011011001100 (
#101500
0!
#102000
b11111111111111111100101001100111 1
b0 #
b0 (
b0 '
b0 $
b11001010011001111110101110010010 %
b0 +
0-
b11100 .
1)
02
10
b110110010011101001000011100110 ,
13
b11100 /
b10 *
1!
#102500
0!
#103000
b0 .
b0 1
00
0)
b0 ,
03
b0 /
b0 *
1!
#103100
1-
12
b101101110100010101010010100010 +
b10 $
b10110 '
b0 %
b100001001011 #
b101101110100010100110001010111 (
#103500
0!
#104000
b11111111111111111100100111010011 1
b0 #
b0 (
b0 '
b0 $
b11001001110100110001011101111101 %
b0 +
0-
b10110 .
1)
02
10
b101101110100010101010010100010 ,
13
b10110 /
b10 *
1!
#104500
0!
#105000
b0 .
b0 1
00
0)
b0 ,
03
b0 /
b0 *
1!
#105100
1-
12
b100001110110100010011110001 +
b100 $
b111 '
b0 %
b111101001111 #
b100001110110011010110100010 (
#105500
0!
#106000
b111111 1
b0 #
b0 (
b0 '
b0 $
b111101101010100011111111101111 %
b0 +
0-
b111 .
1)
02
10
b100001110110100010011110001 ,
13
b111 /
b100 *
1!
#106500
0!
#107000
b0 .
b0 1
00
0)
b0 ,
03
b0 /
b0 *
1!
#107100
1-
12
b101101100000101010011001000110 +
b101 $
b11 '
b0 %
b10111100111 #
b101101100000101010000001011111 (
#107500
0!
#108000
b1101111010110010 1
b0 #
b0 (
b0 '
b0 $
b11011110101100100010011101101100 %
b0 +
0-
b11 .
1)
02
10
b101101100000101010011001000110 ,
13
b11 /
b101 *
1!
#108500
0!
#109000
b0 .
b0 1
00
0)
b0 ,
03
b0 /
b0 *
1!
#109100
1-
12
b111101010000010100111100110100 +
b100 $
b11010 '
b0 %
b100011011 #
b111101010000010100111000011001 (
#109500
0!
#110000
b111110 1
b0 #
b0 (
b0 '
b0 $
b1101000110111011111001000111110 %
b0 +
0-
b11010 .
1)
02
10
b111101010000010100111100110100 ,
13
b11010 /
b100 *
1!
#110500
0!
#111000
b0 .
b0 1
00
0)
b0 ,
03
b0 /
b0 *
1!
#111100
1-
12
b11100111111010101000111100011 +
b10 $
b11000 '
b0 %
b100101101001 #
b11100111111010100100001111010 (
#111500
0!
#112000
b110110110110110 1
b0 #
b0 (
b0 '
b0 $
b1101101101101100000101000000111 %
b0 +
0-
b11000 .
1)
02
10
b11100111111010101000111100011 ,
13
b11000 /
b10 *
1!
#112500
0!
#113000
b0 .
b0 1
00
0)
b0 ,
03
b0 /
b0 *
1!
#113100
b11101 '
b0 %
b100000010100 #
b110100000101001001011011100000 (
#113500
0!
#114000
b11101 /
1!
#114100
1-
12
b110000111111100101010010110011 +
b10 $
b10010 '
b110100011110 #
b110000111111100100011110010101 (
#114500
0!
#115000
b1000110010111 1
b0 #
b0 (
b0 '
b0 $
b10001100101110001001111101100 %
b0 +
0-
b10010 .
1)
02
10
b110000111111100101010010110011 ,
13
b10010 /
b10 *
1!
#115500
0!
#116000
b0 .
b0 1
00
0)
b0 ,
03
b0 /
b0 *
1!
#116100
1-
12
b1110000101000111100101010111 +
b1 $
b11110 '
b0 %
b100111000100 #
b1110000101000110111110010011 (
#116500
0!
#117000
b1110010 1
b0 #
b0 (
b0 '
b0 $
b1110010100110100010000011001000 %
b0 +
0-
b11110 .
1)
02
10
b1110000101000111100101010111 ,
13
b11110 /
b1 *
1!
#117500
0!
#118000
b0 .
b0 1
00
0)
b0 ,
03
b0 /
b0 *
1!
#118100
1-
12
b10100011100001100100101011010 +
b11 $
b11101 '
b0 %
b101100001101 #
b10100011100001011111001001101 (
#118500
0!
#119000
b1110010101111001101011010111 1
b0 #
b0 (
b0 '
b0 $
b1110010101111001101011010111 %
b0 +
0-
b11101 .
1)
02
10
b10100011100001100100101011010 ,
13
b11101 /
b11 *
1!
#119500
0!
#120000
b0 .
b0 1
00
0)
b0 ,
03
b0 /
b0 *
1!
#120100
b11001 '
b0 %
b100001010101 #
b10000111100001010001101110011 (
#120500
0!
#121000
b11001 /
1!
#121100
1-
12
b1011000010010010110100001011 +
b101 $
b1011 '
b101100011 #
b1011000010010010101110101000 (
#121500
0!
#122000
b1001000001001100 1
b0 #
b0 (
b0 '
b0 $
b10010000010011001110100101110000 %
b0 +
0-
b1011 .
1)
02
10
b1011000010010010110100001011 ,
13
b1011 /
b101 *
1!
#122500
0!
#123000
b0 .
b0 1
00
0)
b0 ,
03
b0 /
b0 *
1!
#123100
1-
12
b111000010001010100100000100011 +
b11 $
b1100 '
b0 %
b100001010111 #
b111000010001010011111111001100 (
#123500
0!
